{
"meta":{"test_sets":[],"test_metrics":[],"learn_metrics":[{"best_value":"Min","name":"Logloss"}],"launch_mode":"Train","parameters":"","iteration_count":1000,"learn_sets":["learn"],"name":"experiment"},
"iterations":[
{"learn":[0.6879263889],"iteration":0,"passed_time":0.1762513785,"remaining_time":176.0751271},
{"learn":[0.6827723471],"iteration":1,"passed_time":0.2247944952,"remaining_time":112.1724531},
{"learn":[0.6770775613],"iteration":2,"passed_time":0.2600617736,"remaining_time":86.4271961},
{"learn":[0.6711259478],"iteration":3,"passed_time":0.2655426579,"remaining_time":66.12012181},
{"learn":[0.6664080673],"iteration":4,"passed_time":0.3773401984,"remaining_time":75.09069947},
{"learn":[0.6608825855],"iteration":5,"passed_time":0.4140417445,"remaining_time":68.59291567},
{"learn":[0.6553442451],"iteration":6,"passed_time":0.4312464078,"remaining_time":61.17538327},
{"learn":[0.6498806557],"iteration":7,"passed_time":0.4714300442,"remaining_time":58.45732548},
{"learn":[0.6454434341],"iteration":8,"passed_time":0.4848627766,"remaining_time":53.38877907},
{"learn":[0.6406481454],"iteration":9,"passed_time":0.5554699112,"remaining_time":54.99152121},
{"learn":[0.6366679588],"iteration":10,"passed_time":0.5904775916,"remaining_time":53.08930346},
{"learn":[0.631712067],"iteration":11,"passed_time":0.6089519312,"remaining_time":50.13704234},
{"learn":[0.6266243752],"iteration":12,"passed_time":0.6752787376,"remaining_time":51.26923954},
{"learn":[0.6223110242],"iteration":13,"passed_time":0.6810114901,"remaining_time":47.96266637},
{"learn":[0.6184038741],"iteration":14,"passed_time":0.68881082,"remaining_time":45.23191051},
{"learn":[0.6136197722],"iteration":15,"passed_time":0.6959611768,"remaining_time":42.80161237},
{"learn":[0.6091979809],"iteration":16,"passed_time":0.7065742135,"remaining_time":40.85661481},
{"learn":[0.6059528308],"iteration":17,"passed_time":0.7416904925,"remaining_time":40.46333687},
{"learn":[0.6010947067],"iteration":18,"passed_time":0.7900819005,"remaining_time":40.79317602},
{"learn":[0.5964371756],"iteration":19,"passed_time":0.9347173476,"remaining_time":45.80115003},
{"learn":[0.5940929799],"iteration":20,"passed_time":0.9615244372,"remaining_time":44.82535353},
{"learn":[0.5900653025],"iteration":21,"passed_time":1.05199224,"remaining_time":46.76583686},
{"learn":[0.5866867237],"iteration":22,"passed_time":1.091242228,"remaining_time":46.35407204},
{"learn":[0.5826267714],"iteration":23,"passed_time":1.134548124,"remaining_time":46.13829039},
{"learn":[0.5787951009],"iteration":24,"passed_time":1.140131233,"remaining_time":44.46511807},
{"learn":[0.5750727707],"iteration":25,"passed_time":1.157193481,"remaining_time":43.35024811},
{"learn":[0.5711904804],"iteration":26,"passed_time":1.187768991,"remaining_time":42.80367513},
{"learn":[0.5675020539],"iteration":27,"passed_time":1.213129149,"remaining_time":42.11291189},
{"learn":[0.5641866105],"iteration":28,"passed_time":1.236979217,"remaining_time":41.41747654},
{"learn":[0.5608562941],"iteration":29,"passed_time":1.2513247,"remaining_time":40.45949862},
{"learn":[0.5579405367],"iteration":30,"passed_time":1.267499822,"remaining_time":39.61959122},
{"learn":[0.5546432238],"iteration":31,"passed_time":1.27896911,"remaining_time":38.68881559},
{"learn":[0.5516167116],"iteration":32,"passed_time":1.288898975,"remaining_time":37.76864572},
{"learn":[0.5488198527],"iteration":33,"passed_time":1.314491882,"remaining_time":37.34703405},
{"learn":[0.5456853288],"iteration":34,"passed_time":1.324001724,"remaining_time":36.50461897},
{"learn":[0.5425397894],"iteration":35,"passed_time":1.340096398,"remaining_time":35.88480355},
{"learn":[0.5402172817],"iteration":36,"passed_time":1.345958417,"remaining_time":35.0312961},
{"learn":[0.5370518974],"iteration":37,"passed_time":1.353584779,"remaining_time":34.26706731},
{"learn":[0.5354091344],"iteration":38,"passed_time":1.357441201,"remaining_time":33.44874343},
{"learn":[0.5319792501],"iteration":39,"passed_time":1.371937975,"remaining_time":32.9265114},
{"learn":[0.5287901632],"iteration":40,"passed_time":1.377207955,"remaining_time":32.21322997},
{"learn":[0.5263579294],"iteration":41,"passed_time":1.384937193,"remaining_time":31.58975789},
{"learn":[0.5241963247],"iteration":42,"passed_time":1.402718111,"remaining_time":31.21863331},
{"learn":[0.522144189],"iteration":43,"passed_time":1.413967091,"remaining_time":30.72164862},
{"learn":[0.519671408],"iteration":44,"passed_time":1.442717152,"remaining_time":30.617664},
{"learn":[0.517162323],"iteration":45,"passed_time":1.460097236,"remaining_time":30.28114702},
{"learn":[0.5148810912],"iteration":46,"passed_time":1.476663831,"remaining_time":29.94171555},
{"learn":[0.5122414921],"iteration":47,"passed_time":1.495807567,"remaining_time":29.66685007},
{"learn":[0.5100233099],"iteration":48,"passed_time":1.502823517,"remaining_time":29.16704418},
{"learn":[0.5078662915],"iteration":49,"passed_time":1.532799563,"remaining_time":29.1231917},
{"learn":[0.5050948068],"iteration":50,"passed_time":1.575831965,"remaining_time":29.32283401},
{"learn":[0.5025049703],"iteration":51,"passed_time":1.605632871,"remaining_time":29.27192234},
{"learn":[0.5003866989],"iteration":52,"passed_time":1.630137808,"remaining_time":29.12717933},
{"learn":[0.4985913052],"iteration":53,"passed_time":1.649569543,"remaining_time":28.89801458},
{"learn":[0.4964553747],"iteration":54,"passed_time":1.688710961,"remaining_time":29.01512469},
{"learn":[0.4938899265],"iteration":55,"passed_time":1.713265257,"remaining_time":28.8807572},
{"learn":[0.4929302087],"iteration":56,"passed_time":1.719857484,"remaining_time":28.45308084},
{"learn":[0.4905535237],"iteration":57,"passed_time":1.749925221,"remaining_time":28.42119928},
{"learn":[0.4883464856],"iteration":58,"passed_time":1.76311832,"remaining_time":28.12024304},
{"learn":[0.4861485342],"iteration":59,"passed_time":1.799380066,"remaining_time":28.1902877},
{"learn":[0.4845354745],"iteration":60,"passed_time":1.815843682,"remaining_time":27.95208552},
{"learn":[0.4836386777],"iteration":61,"passed_time":1.845491731,"remaining_time":27.92050393},
{"learn":[0.482225611],"iteration":62,"passed_time":1.877996714,"remaining_time":27.93147494},
{"learn":[0.4801559448],"iteration":63,"passed_time":1.899366867,"remaining_time":27.77824043},
{"learn":[0.4781625298],"iteration":64,"passed_time":1.922739734,"remaining_time":27.65787155},
{"learn":[0.475933975],"iteration":65,"passed_time":1.935795278,"remaining_time":27.39443621},
{"learn":[0.4738337056],"iteration":66,"passed_time":1.941612196,"remaining_time":27.0376743},
{"learn":[0.4725191781],"iteration":67,"passed_time":1.95500191,"remaining_time":26.79502618},
{"learn":[0.470853184],"iteration":68,"passed_time":1.963494363,"remaining_time":26.49294567},
{"learn":[0.4691653305],"iteration":69,"passed_time":1.974248998,"remaining_time":26.22930811},
{"learn":[0.4675789308],"iteration":70,"passed_time":2.015041548,"remaining_time":26.36582533},
{"learn":[0.4661274599],"iteration":71,"passed_time":2.025408448,"remaining_time":26.10526445},
{"learn":[0.4647521115],"iteration":72,"passed_time":2.032484987,"remaining_time":25.80977511},
{"learn":[0.4638150676],"iteration":73,"passed_time":2.050549795,"remaining_time":25.65958256},
{"learn":[0.4620660932],"iteration":74,"passed_time":2.09050862,"remaining_time":25.78293965},
{"learn":[0.4607466794],"iteration":75,"passed_time":2.115798109,"remaining_time":25.7236507},
{"learn":[0.4599590087],"iteration":76,"passed_time":2.122391263,"remaining_time":25.44113164},
{"learn":[0.4581396124],"iteration":77,"passed_time":2.16290322,"remaining_time":25.56662524},
{"learn":[0.4568413724],"iteration":78,"passed_time":2.196704552,"remaining_time":25.60968218},
{"learn":[0.4552410854],"iteration":79,"passed_time":2.206307407,"remaining_time":25.37253518},
{"learn":[0.454048071],"iteration":80,"passed_time":2.226638376,"remaining_time":25.26272429},
{"learn":[0.4525806556],"iteration":81,"passed_time":2.251136309,"remaining_time":25.20174551},
{"learn":[0.45096691],"iteration":82,"passed_time":2.276690216,"remaining_time":25.15331238},
{"learn":[0.4497306052],"iteration":83,"passed_time":2.310572858,"remaining_time":25.19624688},
{"learn":[0.4487382696],"iteration":84,"passed_time":2.324077597,"remaining_time":25.01801178},
{"learn":[0.447441444],"iteration":85,"passed_time":2.343817554,"remaining_time":24.90987493},
{"learn":[0.4462690032],"iteration":86,"passed_time":2.349107999,"remaining_time":24.65213337},
{"learn":[0.4449107995],"iteration":87,"passed_time":2.367241749,"remaining_time":24.53323268},
{"learn":[0.4439527533],"iteration":88,"passed_time":2.382856337,"remaining_time":24.39081037},
{"learn":[0.4425462444],"iteration":89,"passed_time":2.40406096,"remaining_time":24.30772748},
{"learn":[0.4409294128],"iteration":90,"passed_time":2.427144175,"remaining_time":24.24476984},
{"learn":[0.439900259],"iteration":91,"passed_time":2.436852458,"remaining_time":24.05067426},
{"learn":[0.4390791989],"iteration":92,"passed_time":2.46350456,"remaining_time":24.02579179},
{"learn":[0.4378988716],"iteration":93,"passed_time":2.476343252,"remaining_time":23.86773389},
{"learn":[0.4365185941],"iteration":94,"passed_time":2.517258066,"remaining_time":23.98019526},
{"learn":[0.4357373527],"iteration":95,"passed_time":2.529790855,"remaining_time":23.82219721},
{"learn":[0.434756804],"iteration":96,"passed_time":2.550903554,"remaining_time":23.74707123},
{"learn":[0.4332962036],"iteration":97,"passed_time":2.563881857,"remaining_time":23.59817791},
{"learn":[0.4320653851],"iteration":98,"passed_time":2.5705834,"remaining_time":23.39490549},
{"learn":[0.4309400923],"iteration":99,"passed_time":2.574860019,"remaining_time":23.17374017},
{"learn":[0.4300984586],"iteration":100,"passed_time":2.600061637,"remaining_time":23.14312289},
{"learn":[0.4290107127],"iteration":101,"passed_time":2.605189417,"remaining_time":22.9358833},
{"learn":[0.4280459372],"iteration":102,"passed_time":2.642169643,"remaining_time":23.00996282},
{"learn":[0.4272223483],"iteration":103,"passed_time":2.650640231,"remaining_time":22.83628506},
{"learn":[0.4267098073],"iteration":104,"passed_time":2.668439602,"remaining_time":22.74527089},
{"learn":[0.4253906936],"iteration":105,"passed_time":2.684676142,"remaining_time":22.64245727},
{"learn":[0.4246422414],"iteration":106,"passed_time":2.714747083,"remaining_time":22.65672098},
{"learn":[0.4237013399],"iteration":107,"passed_time":2.745573204,"remaining_time":22.6764009},
{"learn":[0.4229943779],"iteration":108,"passed_time":2.756825059,"remaining_time":22.53514796},
{"learn":[0.4221531729],"iteration":109,"passed_time":2.78004767,"remaining_time":22.49311297},
{"learn":[0.4213151825],"iteration":110,"passed_time":2.785645718,"remaining_time":22.31026165},
{"learn":[0.4202594543],"iteration":111,"passed_time":2.792321495,"remaining_time":22.13912042},
{"learn":[0.4193002508],"iteration":112,"passed_time":2.801137526,"remaining_time":21.98769014},
{"learn":[0.4187675219],"iteration":113,"passed_time":2.808107087,"remaining_time":21.82441122},
{"learn":[0.4176423148],"iteration":114,"passed_time":2.822506425,"remaining_time":21.7210277},
{"learn":[0.4171597341],"iteration":115,"passed_time":2.840653588,"remaining_time":21.64773941},
{"learn":[0.4167504043],"iteration":116,"passed_time":2.85912675,"remaining_time":21.57785402},
{"learn":[0.4162266763],"iteration":117,"passed_time":2.868465,"remaining_time":21.44056042},
{"learn":[0.4154533215],"iteration":118,"passed_time":2.876791991,"remaining_time":21.29793063},
{"learn":[0.4144489417],"iteration":119,"passed_time":2.90664178,"remaining_time":21.31537306},
{"learn":[0.4136220525],"iteration":120,"passed_time":2.928403448,"remaining_time":21.27327794},
{"learn":[0.4128757863],"iteration":121,"passed_time":2.949571016,"remaining_time":21.22724059},
{"learn":[0.4121581517],"iteration":122,"passed_time":2.970728228,"remaining_time":21.18153378},
{"learn":[0.4115682023],"iteration":123,"passed_time":2.993083212,"remaining_time":21.14468463},
{"learn":[0.4109733667],"iteration":124,"passed_time":3.021822729,"remaining_time":21.1527591},
{"learn":[0.4101229035],"iteration":125,"passed_time":3.031331168,"remaining_time":21.02685271},
{"learn":[0.4094859777],"iteration":126,"passed_time":3.062936947,"remaining_time":21.05467681},
{"learn":[0.4087025503],"iteration":127,"passed_time":3.076878652,"remaining_time":20.96123582},
{"learn":[0.4080564092],"iteration":128,"passed_time":3.112747256,"remaining_time":21.01707644},
{"learn":[0.4077717642],"iteration":129,"passed_time":3.117737167,"remaining_time":20.86485643},
{"learn":[0.4073649203],"iteration":130,"passed_time":3.1244726,"remaining_time":20.72646328},
{"learn":[0.4063410384],"iteration":131,"passed_time":3.139025211,"remaining_time":20.64146881},
{"learn":[0.4058873466],"iteration":132,"passed_time":3.146111582,"remaining_time":20.50886272},
{"learn":[0.4051758841],"iteration":133,"passed_time":3.154141947,"remaining_time":20.38423079},
{"learn":[0.4042987609],"iteration":134,"passed_time":3.169793144,"remaining_time":20.31015607},
{"learn":[0.4035083471],"iteration":135,"passed_time":3.198538307,"remaining_time":20.32012572},
{"learn":[0.4030089646],"iteration":136,"passed_time":3.228478236,"remaining_time":20.33705633},
{"learn":[0.4021303413],"iteration":137,"passed_time":3.259430734,"remaining_time":20.35963255},
{"learn":[0.4013304121],"iteration":138,"passed_time":3.29388762,"remaining_time":20.40314562},
{"learn":[0.4006053625],"iteration":139,"passed_time":3.304827113,"remaining_time":20.30108084},
{"learn":[0.4000840348],"iteration":140,"passed_time":3.313880941,"remaining_time":20.18882077},
{"learn":[0.3996103694],"iteration":141,"passed_time":3.354764176,"remaining_time":20.27033566},
{"learn":[0.3991692361],"iteration":142,"passed_time":3.388844454,"remaining_time":20.30936851},
{"learn":[0.3987949671],"iteration":143,"passed_time":3.405657416,"remaining_time":20.2447413},
{"learn":[0.3984248986],"iteration":144,"passed_time":3.41513626,"remaining_time":20.1375276},
{"learn":[0.3976568586],"iteration":145,"passed_time":3.450242875,"remaining_time":20.18155764},
{"learn":[0.3972909477],"iteration":146,"passed_time":3.477710947,"remaining_time":20.18018665},
{"learn":[0.3967510181],"iteration":147,"passed_time":3.513505818,"remaining_time":20.22639836},
{"learn":[0.3961638547],"iteration":148,"passed_time":3.549483286,"remaining_time":20.27255219},
{"learn":[0.3955842779],"iteration":149,"passed_time":3.566387899,"remaining_time":20.20953143},
{"learn":[0.3949115196],"iteration":150,"passed_time":3.582226712,"remaining_time":20.14112899},
{"learn":[0.3945460373],"iteration":151,"passed_time":3.594554091,"remaining_time":20.05382808},
{"learn":[0.3939515875],"iteration":152,"passed_time":3.633736263,"remaining_time":20.11617395},
{"learn":[0.393712676],"iteration":153,"passed_time":3.664550179,"remaining_time":20.1312302},
{"learn":[0.3932437254],"iteration":154,"passed_time":3.697347427,"remaining_time":20.15650694},
{"learn":[0.3924789857],"iteration":155,"passed_time":3.721525394,"remaining_time":20.13440662},
{"learn":[0.392114275],"iteration":156,"passed_time":3.759130831,"remaining_time":20.18437765},
{"learn":[0.391262183],"iteration":157,"passed_time":3.806250116,"remaining_time":20.28394049},
{"learn":[0.3906138559],"iteration":158,"passed_time":3.834336616,"remaining_time":20.28098801},
{"learn":[0.3901524062],"iteration":159,"passed_time":3.868653138,"remaining_time":20.31042898},
{"learn":[0.3898900064],"iteration":160,"passed_time":3.907096823,"remaining_time":20.36058531},
{"learn":[0.389202418],"iteration":161,"passed_time":3.948732654,"remaining_time":20.42616027},
{"learn":[0.3888604668],"iteration":162,"passed_time":3.975896032,"remaining_time":20.41610416},
{"learn":[0.3881964523],"iteration":163,"passed_time":3.987372571,"remaining_time":20.32587482},
{"learn":[0.3876249335],"iteration":164,"passed_time":4.026640973,"remaining_time":20.37724371},
{"learn":[0.3872454354],"iteration":165,"passed_time":4.062572805,"remaining_time":20.41075735},
{"learn":[0.3869864217],"iteration":166,"passed_time":4.102523278,"remaining_time":20.46348438},
{"learn":[0.3861763772],"iteration":167,"passed_time":4.133917103,"remaining_time":20.47273232},
{"learn":[0.3860647652],"iteration":168,"passed_time":4.217675988,"remaining_time":20.73898666},
{"learn":[0.3860352334],"iteration":169,"passed_time":4.237178844,"remaining_time":20.68740259},
{"learn":[0.3857919929],"iteration":170,"passed_time":4.248321843,"remaining_time":20.59566554},
{"learn":[0.38552685],"iteration":171,"passed_time":4.260119416,"remaining_time":20.50801673},
{"learn":[0.3849001681],"iteration":172,"passed_time":4.299197226,"remaining_time":20.55165379},
{"learn":[0.3843555665],"iteration":173,"passed_time":4.320570218,"remaining_time":20.5102931},
{"learn":[0.3838407109],"iteration":174,"passed_time":4.338384471,"remaining_time":20.45238393},
{"learn":[0.3836032567],"iteration":175,"passed_time":4.360464669,"remaining_time":20.41490277},
{"learn":[0.3832643487],"iteration":176,"passed_time":4.372720955,"remaining_time":20.33191721},
{"learn":[0.382861191],"iteration":177,"passed_time":4.378551113,"remaining_time":20.22005065},
{"learn":[0.3826698132],"iteration":178,"passed_time":4.403597098,"remaining_time":20.19750401},
{"learn":[0.3819742096],"iteration":179,"passed_time":4.417433377,"remaining_time":20.12386316},
{"learn":[0.3813458561],"iteration":180,"passed_time":4.431022925,"remaining_time":20.04976672},
{"learn":[0.3809052371],"iteration":181,"passed_time":4.448324944,"remaining_time":19.9930209},
{"learn":[0.3805451554],"iteration":182,"passed_time":4.481516759,"remaining_time":20.00764586},
{"learn":[0.3800636892],"iteration":183,"passed_time":4.506076273,"remaining_time":19.98346869},
{"learn":[0.3799626211],"iteration":184,"passed_time":4.542398985,"remaining_time":20.01110904},
{"learn":[0.3796406864],"iteration":185,"passed_time":4.560249895,"remaining_time":19.95722266},
{"learn":[0.37934344],"iteration":186,"passed_time":4.577349416,"remaining_time":19.90045495},
{"learn":[0.3789503976],"iteration":187,"passed_time":4.593845952,"remaining_time":19.84150486},
{"learn":[0.3783769072],"iteration":188,"passed_time":4.604398346,"remaining_time":19.75749767},
{"learn":[0.3780960769],"iteration":189,"passed_time":4.656431776,"remaining_time":19.85110389},
{"learn":[0.3776186825],"iteration":190,"passed_time":4.67313764,"remaining_time":19.79355157},
{"learn":[0.3774124746],"iteration":191,"passed_time":4.69600512,"remaining_time":19.76235488},
{"learn":[0.3771635334],"iteration":192,"passed_time":4.717959124,"remaining_time":19.72742494},
{"learn":[0.3768111668],"iteration":193,"passed_time":4.738112805,"remaining_time":19.68514908},
{"learn":[0.37641641],"iteration":194,"passed_time":4.744696538,"remaining_time":19.58708058},
{"learn":[0.3762881675],"iteration":195,"passed_time":4.785733917,"remaining_time":19.63127586},
{"learn":[0.375828818],"iteration":196,"passed_time":4.803073097,"remaining_time":19.57800861},
{"learn":[0.3755892636],"iteration":197,"passed_time":4.840453077,"remaining_time":19.60627964},
{"learn":[0.3751470587],"iteration":198,"passed_time":4.853907899,"remaining_time":19.53758908},
{"learn":[0.3748566274],"iteration":199,"passed_time":4.867796535,"remaining_time":19.47118614},
{"learn":[0.3745705251],"iteration":200,"passed_time":4.896810689,"remaining_time":19.46543155},
{"learn":[0.3740999886],"iteration":201,"passed_time":4.910113526,"remaining_time":19.39737918},
{"learn":[0.3737611663],"iteration":202,"passed_time":4.921940973,"remaining_time":19.32407367},
{"learn":[0.3735355849],"iteration":203,"passed_time":4.943640689,"remaining_time":19.2898921},
{"learn":[0.3732791001],"iteration":204,"passed_time":4.958449834,"remaining_time":19.22911033},
{"learn":[0.3730172147],"iteration":205,"passed_time":4.982128676,"remaining_time":19.20296199},
{"learn":[0.3729035453],"iteration":206,"passed_time":5.001068531,"remaining_time":19.15868283},
{"learn":[0.372615257],"iteration":207,"passed_time":5.014440444,"remaining_time":19.09344631},
{"learn":[0.3723489997],"iteration":208,"passed_time":5.029658168,"remaining_time":19.03569192},
{"learn":[0.3717242466],"iteration":209,"passed_time":5.059450433,"remaining_time":19.03317068},
{"learn":[0.3715011082],"iteration":210,"passed_time":5.070475653,"remaining_time":18.96021465},
{"learn":[0.371174673],"iteration":211,"passed_time":5.085709521,"remaining_time":18.90348633},
{"learn":[0.3708412513],"iteration":212,"passed_time":5.124439756,"remaining_time":18.93396285},
{"learn":[0.3704925709],"iteration":213,"passed_time":5.151980505,"remaining_time":18.92269475},
{"learn":[0.3699844017],"iteration":214,"passed_time":5.160508528,"remaining_time":18.84185672},
{"learn":[0.3696252201],"iteration":215,"passed_time":5.169302884,"remaining_time":18.76265491},
{"learn":[0.3692723392],"iteration":216,"passed_time":5.198734721,"remaining_time":18.75856814},
{"learn":[0.3689234016],"iteration":217,"passed_time":5.213907299,"remaining_time":18.70309866},
{"learn":[0.3687845723],"iteration":218,"passed_time":5.226847737,"remaining_time":18.64003691},
{"learn":[0.3685602338],"iteration":219,"passed_time":5.232675036,"remaining_time":18.55221149},
{"learn":[0.3683463107],"iteration":220,"passed_time":5.284081022,"remaining_time":18.62578786},
{"learn":[0.3681042703],"iteration":221,"passed_time":5.296464097,"remaining_time":18.56148229},
{"learn":[0.3679682271],"iteration":222,"passed_time":5.312490518,"remaining_time":18.51033692},
{"learn":[0.3677260581],"iteration":223,"passed_time":5.350275405,"remaining_time":18.53488265},
{"learn":[0.3674225539],"iteration":224,"passed_time":5.363651749,"remaining_time":18.47480047},
{"learn":[0.3671484958],"iteration":225,"passed_time":5.376441137,"remaining_time":18.41312141},
{"learn":[0.3666880747],"iteration":226,"passed_time":5.38204651,"remaining_time":18.32740948},
{"learn":[0.3665723479],"iteration":227,"passed_time":5.39118464,"remaining_time":18.25436203},
{"learn":[0.3661873635],"iteration":228,"passed_time":5.403552717,"remaining_time":18.19274736},
{"learn":[0.3659230779],"iteration":229,"passed_time":5.447669996,"remaining_time":18.23785172},
{"learn":[0.3657866917],"iteration":230,"passed_time":5.462462098,"remaining_time":18.18455997},
{"learn":[0.3655989572],"iteration":231,"passed_time":5.492378766,"remaining_time":18.18166764},
{"learn":[0.3655103619],"iteration":232,"passed_time":5.500626373,"remaining_time":18.10721214},
{"learn":[0.3653324427],"iteration":233,"passed_time":5.51781902,"remaining_time":18.06260414},
{"learn":[0.3651690537],"iteration":234,"passed_time":5.540368753,"remaining_time":18.03566849},
{"learn":[0.364912826],"iteration":235,"passed_time":5.551044606,"remaining_time":17.97033084},
{"learn":[0.3646956026],"iteration":236,"passed_time":5.558234502,"remaining_time":17.89423175},
{"learn":[0.3644581055],"iteration":237,"passed_time":5.61270317,"remaining_time":17.97008326},
{"learn":[0.3641182974],"iteration":238,"passed_time":5.664145311,"remaining_time":18.03520746},
{"learn":[0.364040289],"iteration":239,"passed_time":5.691318043,"remaining_time":18.02250714},
{"learn":[0.3638562835],"iteration":240,"passed_time":5.738604519,"remaining_time":18.07303249},
{"learn":[0.3633894331],"iteration":241,"passed_time":5.823553196,"remaining_time":18.24071621},
{"learn":[0.3631900402],"iteration":242,"passed_time":5.84728817,"remaining_time":18.21562611},
{"learn":[0.3630421671],"iteration":243,"passed_time":5.860573264,"remaining_time":18.15816962},
{"learn":[0.3625921614],"iteration":244,"passed_time":5.87462625,"remaining_time":18.10344008},
{"learn":[0.3624227288],"iteration":245,"passed_time":5.891014281,"remaining_time":18.05619824},
{"learn":[0.3621112952],"iteration":246,"passed_time":5.914306864,"remaining_time":18.03025534},
{"learn":[0.3616883353],"iteration":247,"passed_time":5.947767599,"remaining_time":18.03516627},
{"learn":[0.3614927999],"iteration":248,"passed_time":5.991863144,"remaining_time":18.07184426},
{"learn":[0.3610990717],"iteration":249,"passed_time":6.033368963,"remaining_time":18.10010689},
{"learn":[0.3607392043],"iteration":250,"passed_time":6.047214581,"remaining_time":18.04527379},
{"learn":[0.3605009358],"iteration":251,"passed_time":6.062124466,"remaining_time":17.993925},
{"learn":[0.3602572238],"iteration":252,"passed_time":6.074244211,"remaining_time":17.93462619},
{"learn":[0.3601044644],"iteration":253,"passed_time":6.085045218,"remaining_time":17.87182572},
{"learn":[0.3596767468],"iteration":254,"passed_time":6.127925112,"remaining_time":17.90315376},
{"learn":[0.3595194227],"iteration":255,"passed_time":6.157698631,"remaining_time":17.89581165},
{"learn":[0.3592764608],"iteration":256,"passed_time":6.196071283,"remaining_time":17.9131555},
{"learn":[0.3590344847],"iteration":257,"passed_time":6.216488002,"remaining_time":17.87842674},
{"learn":[0.3586897475],"iteration":258,"passed_time":6.233229612,"remaining_time":17.83329399},
{"learn":[0.358629291],"iteration":259,"passed_time":6.246077692,"remaining_time":17.77729805},
{"learn":[0.3584878043],"iteration":260,"passed_time":6.264167177,"remaining_time":17.73647335},
{"learn":[0.3582659518],"iteration":261,"passed_time":6.310268139,"remaining_time":17.77472476},
{"learn":[0.3579472531],"iteration":262,"passed_time":6.365176773,"remaining_time":17.83701628},
{"learn":[0.3577919006],"iteration":263,"passed_time":6.492121172,"remaining_time":18.0992469},
{"learn":[0.3575829495],"iteration":264,"passed_time":6.511129858,"remaining_time":18.05917149},
{"learn":[0.3574367266],"iteration":265,"passed_time":6.556866939,"remaining_time":18.09300877},
{"learn":[0.35729569],"iteration":266,"passed_time":6.651672622,"remaining_time":18.26095892},
{"learn":[0.3570969185],"iteration":267,"passed_time":6.69041872,"remaining_time":18.27383023},
{"learn":[0.3570572714],"iteration":268,"passed_time":6.694514219,"remaining_time":18.19215574},
{"learn":[0.3568599144],"iteration":269,"passed_time":6.777507364,"remaining_time":18.32437176},
{"learn":[0.3565411514],"iteration":270,"passed_time":6.808247782,"remaining_time":18.31443776},
{"learn":[0.3563976931],"iteration":271,"passed_time":6.828516186,"remaining_time":18.27632273},
{"learn":[0.3562275319],"iteration":272,"passed_time":6.886337143,"remaining_time":18.33834104},
{"learn":[0.3561497378],"iteration":273,"passed_time":6.910059333,"remaining_time":18.30913531},
{"learn":[0.3560915529],"iteration":274,"passed_time":6.934043199,"remaining_time":18.28065934},
{"learn":[0.3559640177],"iteration":275,"passed_time":6.970769618,"remaining_time":18.28564204},
{"learn":[0.3555953851],"iteration":276,"passed_time":6.988688751,"remaining_time":18.24123454},
{"learn":[0.3553125189],"iteration":277,"passed_time":7.015214397,"remaining_time":18.21936976},
{"learn":[0.3552119866],"iteration":278,"passed_time":7.068479689,"remaining_time":18.26657296},
{"learn":[0.3548417681],"iteration":279,"passed_time":7.084199716,"remaining_time":18.21651356},
{"learn":[0.354732342],"iteration":280,"passed_time":7.095463461,"remaining_time":18.15529619},
{"learn":[0.3546667206],"iteration":281,"passed_time":7.140870827,"remaining_time":18.18136615},
{"learn":[0.3545923769],"iteration":282,"passed_time":7.169795634,"remaining_time":18.16517127},
{"learn":[0.3544925304],"iteration":283,"passed_time":7.196812488,"remaining_time":18.14407656},
{"learn":[0.3544001204],"iteration":284,"passed_time":7.221052073,"remaining_time":18.11597275},
{"learn":[0.3543267839],"iteration":285,"passed_time":7.269434129,"remaining_time":18.14816772},
{"learn":[0.3542355312],"iteration":286,"passed_time":7.293431167,"remaining_time":18.11922098},
{"learn":[0.3541227405],"iteration":287,"passed_time":7.311099777,"remaining_time":18.07466334},
{"learn":[0.3538898511],"iteration":288,"passed_time":7.324884074,"remaining_time":18.02073556},
{"learn":[0.3537358916],"iteration":289,"passed_time":7.365392467,"remaining_time":18.03251259},
{"learn":[0.3536186433],"iteration":290,"passed_time":7.395657226,"remaining_time":18.01897242},
{"learn":[0.3535045452],"iteration":291,"passed_time":7.448141098,"remaining_time":18.05919143},
{"learn":[0.3533230899],"iteration":292,"passed_time":7.483395496,"remaining_time":18.05720347},
{"learn":[0.3532091419],"iteration":293,"passed_time":7.539302187,"remaining_time":18.1045828},
{"learn":[0.3530932651],"iteration":294,"passed_time":7.580244333,"remaining_time":18.11549917},
{"learn":[0.3528135278],"iteration":295,"passed_time":7.592596806,"remaining_time":18.05806808},
{"learn":[0.3527195105],"iteration":296,"passed_time":7.613309189,"remaining_time":18.02072849},
{"learn":[0.3526227715],"iteration":297,"passed_time":7.682519782,"remaining_time":18.09774794},
{"learn":[0.3524684692],"iteration":298,"passed_time":7.701643203,"remaining_time":18.05636082},
{"learn":[0.3522878283],"iteration":299,"passed_time":7.726882006,"remaining_time":18.02939135},
{"learn":[0.3521855815],"iteration":300,"passed_time":7.743281217,"remaining_time":17.98190555},
{"learn":[0.3521023654],"iteration":301,"passed_time":7.751876348,"remaining_time":17.91658838},
{"learn":[0.3520763912],"iteration":302,"passed_time":7.758872335,"remaining_time":17.84796705},
{"learn":[0.3519481059],"iteration":303,"passed_time":7.771288719,"remaining_time":17.79216102},
{"learn":[0.3518600678],"iteration":304,"passed_time":7.782660021,"remaining_time":17.73425808},
{"learn":[0.3516962287],"iteration":305,"passed_time":7.793635341,"remaining_time":17.6757612},
{"learn":[0.3515029436],"iteration":306,"passed_time":7.813524167,"remaining_time":17.63769462},
{"learn":[0.3514347505],"iteration":307,"passed_time":7.822603888,"remaining_time":17.57546068},
{"learn":[0.3511276459],"iteration":308,"passed_time":7.833797066,"remaining_time":17.518297},
{"learn":[0.3509578276],"iteration":309,"passed_time":7.869212946,"remaining_time":17.51534494},
{"learn":[0.3509083651],"iteration":310,"passed_time":7.887238767,"remaining_time":17.47365759},
{"learn":[0.350483155],"iteration":311,"passed_time":7.922224108,"remaining_time":17.46951983},
{"learn":[0.3503814011],"iteration":312,"passed_time":7.931130674,"remaining_time":17.40794496},
{"learn":[0.3502781472],"iteration":313,"passed_time":7.942502834,"remaining_time":17.35209218},
{"learn":[0.3502284704],"iteration":314,"passed_time":7.95482021,"remaining_time":17.29857728},
{"learn":[0.3498291487],"iteration":315,"passed_time":7.963929539,"remaining_time":17.23837913},
{"learn":[0.3497647703],"iteration":316,"passed_time":8.002549207,"remaining_time":17.24208552},
{"learn":[0.3495632557],"iteration":317,"passed_time":8.022384675,"remaining_time":17.20524009},
{"learn":[0.3495103215],"iteration":318,"passed_time":8.040509666,"remaining_time":17.16484979},
{"learn":[0.3493404817],"iteration":319,"passed_time":8.057383125,"remaining_time":17.12193914},
{"learn":[0.3492579085],"iteration":320,"passed_time":8.072612207,"remaining_time":17.07571243},
{"learn":[0.3491890725],"iteration":321,"passed_time":8.10801714,"remaining_time":17.07216031},
{"learn":[0.3491156717],"iteration":322,"passed_time":8.130128082,"remaining_time":17.04054709},
{"learn":[0.3489536757],"iteration":323,"passed_time":8.153400395,"remaining_time":17.01141564},
{"learn":[0.3488340485],"iteration":324,"passed_time":8.185025076,"remaining_time":16.99966746},
{"learn":[0.3486875255],"iteration":325,"passed_time":8.201764774,"remaining_time":16.95702288},
{"learn":[0.3486088099],"iteration":326,"passed_time":8.212773029,"remaining_time":16.90274082},
{"learn":[0.3485148569],"iteration":327,"passed_time":8.235492254,"remaining_time":16.87271584},
{"learn":[0.3482783457],"iteration":328,"passed_time":8.264877636,"remaining_time":16.85633098},
{"learn":[0.3481020981],"iteration":329,"passed_time":8.279171195,"remaining_time":16.80922636},
{"learn":[0.3480052948],"iteration":330,"passed_time":8.321264176,"remaining_time":16.81850675},
{"learn":[0.3476610934],"iteration":331,"passed_time":8.330761959,"remaining_time":16.76189454},
{"learn":[0.3475138203],"iteration":332,"passed_time":8.351358973,"remaining_time":16.7277971},
{"learn":[0.3474458416],"iteration":333,"passed_time":8.389578231,"remaining_time":16.72891947},
{"learn":[0.3474018868],"iteration":334,"passed_time":8.461997637,"remaining_time":16.7976968},
{"learn":[0.3473101841],"iteration":335,"passed_time":8.487868161,"remaining_time":16.77364422},
{"learn":[0.3472654793],"iteration":336,"passed_time":8.504801445,"remaining_time":16.7319981},
{"learn":[0.3470835954],"iteration":337,"passed_time":8.518770936,"remaining_time":16.68469337},
{"learn":[0.3467908281],"iteration":338,"passed_time":8.535843756,"remaining_time":16.64363635},
{"learn":[0.3466945177],"iteration":339,"passed_time":8.589432746,"remaining_time":16.67360474},
{"learn":[0.3465579387],"iteration":340,"passed_time":8.606626127,"remaining_time":16.63274668},
{"learn":[0.3464340467],"iteration":341,"passed_time":8.616312914,"remaining_time":16.5775845},
{"learn":[0.3463775549],"iteration":342,"passed_time":8.638897812,"remaining_time":16.54739318},
{"learn":[0.3462734865],"iteration":343,"passed_time":8.657467034,"remaining_time":16.5095883},
{"learn":[0.3461921135],"iteration":344,"passed_time":8.681129128,"remaining_time":16.481564},
{"learn":[0.3460883666],"iteration":345,"passed_time":8.739628807,"remaining_time":16.51941399},
{"learn":[0.3460337607],"iteration":346,"passed_time":8.75643882,"remaining_time":16.47825519},
{"learn":[0.3458632137],"iteration":347,"passed_time":8.77338317,"remaining_time":16.43748801},
{"learn":[0.3458223236],"iteration":348,"passed_time":8.784006195,"remaining_time":16.385066},
{"learn":[0.3457642673],"iteration":349,"passed_time":8.801713128,"remaining_time":16.34603867},
{"learn":[0.3456719645],"iteration":350,"passed_time":8.815875001,"remaining_time":16.30057799},
{"learn":[0.3455423077],"iteration":351,"passed_time":8.830270701,"remaining_time":16.25572561},
{"learn":[0.3452640491],"iteration":352,"passed_time":8.839011895,"remaining_time":16.20068186},
{"learn":[0.3451080322],"iteration":353,"passed_time":8.848737859,"remaining_time":16.14769677},
{"learn":[0.3450279236],"iteration":354,"passed_time":8.866417353,"remaining_time":16.10940618},
{"learn":[0.3449154757],"iteration":355,"passed_time":8.879010918,"remaining_time":16.06203099},
{"learn":[0.344733849],"iteration":356,"passed_time":8.93597698,"remaining_time":16.09477086},
{"learn":[0.3446771215],"iteration":357,"passed_time":8.956717895,"remaining_time":16.06204717},
{"learn":[0.3445675453],"iteration":358,"passed_time":8.965928849,"remaining_time":16.00880332},
{"learn":[0.3445105392],"iteration":359,"passed_time":8.976199822,"remaining_time":15.95768857},
{"learn":[0.3444198866],"iteration":360,"passed_time":8.985371738,"remaining_time":15.90485468},
{"learn":[0.3443695025],"iteration":361,"passed_time":8.996659737,"remaining_time":15.85599147},
{"learn":[0.3442795571],"iteration":362,"passed_time":9.002125469,"remaining_time":15.79711825},
{"learn":[0.3441594799],"iteration":363,"passed_time":9.010303757,"remaining_time":15.74327799},
{"learn":[0.3440839575],"iteration":364,"passed_time":9.024171151,"remaining_time":15.69958543},
{"learn":[0.344042703],"iteration":365,"passed_time":9.067350922,"remaining_time":15.70683193},
{"learn":[0.343956808],"iteration":366,"passed_time":9.10355467,"remaining_time":15.70177141},
{"learn":[0.3436218005],"iteration":367,"passed_time":9.116813861,"remaining_time":15.65713685},
{"learn":[0.3435321336],"iteration":368,"passed_time":9.128971223,"remaining_time":15.61078819},
{"learn":[0.343417457],"iteration":369,"passed_time":9.139414948,"remaining_time":15.56170653},
{"learn":[0.3432459456],"iteration":370,"passed_time":9.152151643,"remaining_time":15.51672071},
{"learn":[0.3430677693],"iteration":371,"passed_time":9.18537511,"remaining_time":15.50649346},
{"learn":[0.3430226572],"iteration":372,"passed_time":9.213549412,"remaining_time":15.48765545},
{"learn":[0.3429250824],"iteration":373,"passed_time":9.2363114,"remaining_time":15.45970839},
{"learn":[0.342892036],"iteration":374,"passed_time":9.271475386,"remaining_time":15.45245898},
{"learn":[0.3426112057],"iteration":375,"passed_time":9.289724435,"remaining_time":15.41698949},
{"learn":[0.3423947752],"iteration":376,"passed_time":9.306011971,"remaining_time":15.37836991},
{"learn":[0.3422642397],"iteration":377,"passed_time":9.313732771,"remaining_time":15.32577191},
{"learn":[0.3420516025],"iteration":378,"passed_time":9.321544619,"remaining_time":15.27355992},
{"learn":[0.3419976824],"iteration":379,"passed_time":9.332528452,"remaining_time":15.22675695},
{"learn":[0.341702922],"iteration":380,"passed_time":9.347944517,"remaining_time":15.18734293},
{"learn":[0.3415052007],"iteration":381,"passed_time":9.390038499,"remaining_time":15.19121412},
{"learn":[0.3413024859],"iteration":382,"passed_time":9.40705291,"remaining_time":15.15444294},
{"learn":[0.3411210521],"iteration":383,"passed_time":9.425501227,"remaining_time":15.12007488},
{"learn":[0.34106171],"iteration":384,"passed_time":9.432043582,"remaining_time":15.06677092},
{"learn":[0.3409828872],"iteration":385,"passed_time":9.443320633,"remaining_time":15.02124059},
{"learn":[0.3408232914],"iteration":386,"passed_time":9.475039838,"remaining_time":15.00826724},
{"learn":[0.3407408468],"iteration":387,"passed_time":9.530302531,"remaining_time":15.03233286},
{"learn":[0.3406385143],"iteration":388,"passed_time":9.546195256,"remaining_time":14.99415245},
{"learn":[0.3405691425],"iteration":389,"passed_time":9.570809817,"remaining_time":14.96972817},
{"learn":[0.3405305241],"iteration":390,"passed_time":9.580281034,"remaining_time":14.9217165},
{"learn":[0.3402088251],"iteration":391,"passed_time":9.607062626,"remaining_time":14.9007502},
{"learn":[0.3400282699],"iteration":392,"passed_time":9.626505052,"remaining_time":14.86841874},
{"learn":[0.3399713066],"iteration":393,"passed_time":9.635831445,"remaining_time":14.82059354},
{"learn":[0.3398462146],"iteration":394,"passed_time":9.687482339,"remaining_time":14.8377894},
{"learn":[0.3397966878],"iteration":395,"passed_time":9.738279011,"remaining_time":14.85333465},
{"learn":[0.3397083711],"iteration":396,"passed_time":9.765021285,"remaining_time":14.83200966},
{"learn":[0.3396252407],"iteration":397,"passed_time":9.793787839,"remaining_time":14.81371929},
{"learn":[0.3394900547],"iteration":398,"passed_time":9.805077454,"remaining_time":14.7690515},
{"learn":[0.3392891187],"iteration":399,"passed_time":9.816176014,"remaining_time":14.72426402},
{"learn":[0.3391578331],"iteration":400,"passed_time":9.855993532,"remaining_time":14.72254395},
{"learn":[0.338972906],"iteration":401,"passed_time":9.891797217,"remaining_time":14.71466352},
{"learn":[0.3389092778],"iteration":402,"passed_time":9.916346017,"remaining_time":14.68997164},
{"learn":[0.3388554862],"iteration":403,"passed_time":9.95042673,"remaining_time":14.6793424},
{"learn":[0.3386620939],"iteration":404,"passed_time":9.962647186,"remaining_time":14.63648167},
{"learn":[0.3385106419],"iteration":405,"passed_time":9.972057936,"remaining_time":14.58966112},
{"learn":[0.3382408699],"iteration":406,"passed_time":9.986045502,"remaining_time":14.54969283},
{"learn":[0.3381904002],"iteration":407,"passed_time":9.99897683,"remaining_time":14.50831932},
{"learn":[0.3381183281],"iteration":408,"passed_time":10.01594802,"remaining_time":14.47292245},
{"learn":[0.3380077662],"iteration":409,"passed_time":10.04517164,"remaining_time":14.455247},
{"learn":[0.3378838957],"iteration":410,"passed_time":10.06602043,"remaining_time":14.42551347},
{"learn":[0.3378252179],"iteration":411,"passed_time":10.08026769,"remaining_time":14.38640146},
{"learn":[0.3377177849],"iteration":412,"passed_time":10.09419142,"remaining_time":14.34695004},
{"learn":[0.3374865886],"iteration":413,"passed_time":10.10232754,"remaining_time":14.2994298},
{"learn":[0.3374314469],"iteration":414,"passed_time":10.11211065,"remaining_time":14.25442104},
{"learn":[0.3373356294],"iteration":415,"passed_time":10.13020179,"remaining_time":14.22124482},
{"learn":[0.3372336398],"iteration":416,"passed_time":10.17506335,"remaining_time":14.22556818},
{"learn":[0.336990635],"iteration":417,"passed_time":10.19014511,"remaining_time":14.18819248},
{"learn":[0.3368989323],"iteration":418,"passed_time":10.22629221,"remaining_time":14.18013311},
{"learn":[0.3368281032],"iteration":419,"passed_time":10.25999197,"remaining_time":14.16856034},
{"learn":[0.3367659322],"iteration":420,"passed_time":10.27466084,"remaining_time":14.13070933},
{"learn":[0.3366050506],"iteration":421,"passed_time":10.28686104,"remaining_time":14.08958692},
{"learn":[0.336486645],"iteration":422,"passed_time":10.29658136,"remaining_time":14.04521854},
{"learn":[0.3363686251],"iteration":423,"passed_time":10.40894105,"remaining_time":14.14044821},
{"learn":[0.3363330284],"iteration":424,"passed_time":10.4310313,"remaining_time":14.11257176},
{"learn":[0.3363027037],"iteration":425,"passed_time":10.44099726,"remaining_time":14.06838598},
{"learn":[0.3362733648],"iteration":426,"passed_time":10.46463133,"remaining_time":14.04270199},
{"learn":[0.336213787],"iteration":427,"passed_time":10.47785717,"remaining_time":14.00311752},
{"learn":[0.3360872162],"iteration":428,"passed_time":10.49642756,"remaining_time":13.97076955},
{"learn":[0.3360244665],"iteration":429,"passed_time":10.52004476,"remaining_time":13.94517562},
{"learn":[0.3359621455],"iteration":430,"passed_time":10.53486106,"remaining_time":13.90797202},
{"learn":[0.3359199052],"iteration":431,"passed_time":10.56411462,"remaining_time":13.88985441},
{"learn":[0.3358430112],"iteration":432,"passed_time":10.58851239,"remaining_time":13.86532685},
{"learn":[0.335807436],"iteration":433,"passed_time":10.62848954,"remaining_time":13.8611177},
{"learn":[0.3357750539],"iteration":434,"passed_time":10.67318638,"remaining_time":13.86287426},
{"learn":[0.3357132901],"iteration":435,"passed_time":10.71045431,"remaining_time":13.85480787},
{"learn":[0.3356585128],"iteration":436,"passed_time":10.73179398,"remaining_time":13.82608697},
{"learn":[0.3354182726],"iteration":437,"passed_time":10.74624153,"remaining_time":13.78855648},
{"learn":[0.3350554263],"iteration":438,"passed_time":10.75831847,"remaining_time":13.74810173},
{"learn":[0.3348834434],"iteration":439,"passed_time":10.76768965,"remaining_time":13.70433228},
{"learn":[0.3347357203],"iteration":440,"passed_time":10.80668043,"remaining_time":13.69826385},
{"learn":[0.3345456713],"iteration":441,"passed_time":10.8286021,"remaining_time":13.67049768},
{"learn":[0.3343564794],"iteration":442,"passed_time":10.85227146,"remaining_time":13.64495532},
{"learn":[0.3342653767],"iteration":443,"passed_time":10.87346837,"remaining_time":13.61632526},
{"learn":[0.3340662838],"iteration":444,"passed_time":10.90498202,"remaining_time":13.60059555},
{"learn":[0.3339974907],"iteration":445,"passed_time":10.91421434,"remaining_time":13.55711826},
{"learn":[0.3339376128],"iteration":446,"passed_time":10.93326229,"remaining_time":13.52593746},
{"learn":[0.3338834784],"iteration":447,"passed_time":10.94954068,"remaining_time":13.49139833},
{"learn":[0.3337658657],"iteration":448,"passed_time":10.95886704,"remaining_time":13.44840921},
{"learn":[0.3336688052],"iteration":449,"passed_time":10.9761625,"remaining_time":13.41530972},
{"learn":[0.3335477207],"iteration":450,"passed_time":11.00725523,"remaining_time":13.39907566},
{"learn":[0.3334771917],"iteration":451,"passed_time":11.02225875,"remaining_time":13.36326946},
{"learn":[0.333372159],"iteration":452,"passed_time":11.04688556,"remaining_time":13.33917527},
{"learn":[0.3333178745],"iteration":453,"passed_time":11.06504515,"remaining_time":13.30730099},
{"learn":[0.3331384123],"iteration":454,"passed_time":11.11792042,"remaining_time":13.31706952},
{"learn":[0.3328476381],"iteration":455,"passed_time":11.13541376,"remaining_time":13.28435326},
{"learn":[0.3325346829],"iteration":456,"passed_time":11.14952754,"remaining_time":13.24768809},
{"learn":[0.3324416086],"iteration":457,"passed_time":11.17483391,"remaining_time":13.22436677},
{"learn":[0.332346134],"iteration":458,"passed_time":11.19165792,"remaining_time":13.19103907},
{"learn":[0.3322157699],"iteration":459,"passed_time":11.21819201,"remaining_time":13.16918193},
{"learn":[0.3321455195],"iteration":460,"passed_time":11.24893838,"remaining_time":13.15222947},
{"learn":[0.3320718187],"iteration":461,"passed_time":11.26065513,"remaining_time":13.11305728},
{"learn":[0.3320236635],"iteration":462,"passed_time":11.30957838,"remaining_time":13.11715678},
{"learn":[0.3319411546],"iteration":463,"passed_time":11.32554778,"remaining_time":13.08296037},
{"learn":[0.3318291353],"iteration":464,"passed_time":11.33796625,"remaining_time":13.04475687},
{"learn":[0.3317243383],"iteration":465,"passed_time":11.35480848,"remaining_time":13.01173332},
{"learn":[0.3314636745],"iteration":466,"passed_time":11.38307708,"remaining_time":12.99182031},
{"learn":[0.331255602],"iteration":467,"passed_time":11.39090866,"remaining_time":12.94863975},
{"learn":[0.3311572557],"iteration":468,"passed_time":11.40383229,"remaining_time":12.91137515},
{"learn":[0.3311270382],"iteration":469,"passed_time":11.4137916,"remaining_time":12.87087138},
{"learn":[0.331055309],"iteration":470,"passed_time":11.43902477,"remaining_time":12.84765202},
{"learn":[0.3309658351],"iteration":471,"passed_time":11.47718636,"remaining_time":12.83888644},
{"learn":[0.3309147224],"iteration":472,"passed_time":11.50891471,"remaining_time":12.82282887},
{"learn":[0.3307792364],"iteration":473,"passed_time":11.53470606,"remaining_time":12.80011685},
{"learn":[0.3306598878],"iteration":474,"passed_time":11.55049974,"remaining_time":12.76634182},
{"learn":[0.3305899159],"iteration":475,"passed_time":11.56955494,"remaining_time":12.73623275},
{"learn":[0.3304895551],"iteration":476,"passed_time":11.59234601,"remaining_time":12.71026617},
{"learn":[0.3304544942],"iteration":477,"passed_time":11.60745866,"remaining_time":12.67592766},
{"learn":[0.3303522689],"iteration":478,"passed_time":11.62751353,"remaining_time":12.64704499},
{"learn":[0.3302529153],"iteration":479,"passed_time":11.71019763,"remaining_time":12.68604743},
{"learn":[0.330178743],"iteration":480,"passed_time":11.734364,"remaining_time":12.66140315},
{"learn":[0.3301394602],"iteration":481,"passed_time":11.74986409,"remaining_time":12.6274473},
{"learn":[0.3300519793],"iteration":482,"passed_time":11.76465585,"remaining_time":12.59280968},
{"learn":[0.3299895297],"iteration":483,"passed_time":11.81221647,"remaining_time":12.59318946},
{"learn":[0.3297732064],"iteration":484,"passed_time":11.83002188,"remaining_time":12.56177581},
{"learn":[0.3297502325],"iteration":485,"passed_time":11.84973661,"remaining_time":12.53243749},
{"learn":[0.3296710668],"iteration":486,"passed_time":11.87932624,"remaining_time":12.51354079},
{"learn":[0.3295349807],"iteration":487,"passed_time":11.90919146,"remaining_time":12.4948894},
{"learn":[0.3295017628],"iteration":488,"passed_time":11.93630523,"remaining_time":12.47331692},
{"learn":[0.3293175858],"iteration":489,"passed_time":11.97010006,"remaining_time":12.45867557},
{"learn":[0.3292622941],"iteration":490,"passed_time":11.98644875,"remaining_time":12.4258705},
{"learn":[0.3291526537],"iteration":491,"passed_time":11.99347801,"remaining_time":12.38350981},
{"learn":[0.3287862285],"iteration":492,"passed_time":12.00479904,"remaining_time":12.34570611},
{"learn":[0.3285315224],"iteration":493,"passed_time":12.02161141,"remaining_time":12.31363436},
{"learn":[0.3284638437],"iteration":494,"passed_time":12.06894477,"remaining_time":12.31276184},
{"learn":[0.3280990901],"iteration":495,"passed_time":12.08182241,"remaining_time":12.27669052},
{"learn":[0.3280211459],"iteration":496,"passed_time":12.0947511,"remaining_time":12.24076419},
{"learn":[0.3279678688],"iteration":497,"passed_time":12.12455183,"remaining_time":12.22193779},
{"learn":[0.3278924535],"iteration":498,"passed_time":12.1485167,"remaining_time":12.19720814},
{"learn":[0.3276594783],"iteration":499,"passed_time":12.15751631,"remaining_time":12.15751631},
{"learn":[0.3275906638],"iteration":500,"passed_time":12.18112089,"remaining_time":12.13249366},
{"learn":[0.3274573851],"iteration":501,"passed_time":12.18998764,"remaining_time":12.09285627},
{"learn":[0.3273866632],"iteration":502,"passed_time":12.23324743,"remaining_time":12.087324},
{"learn":[0.327320206],"iteration":503,"passed_time":12.24561506,"remaining_time":12.05124022},
{"learn":[0.3272664788],"iteration":504,"passed_time":12.26380407,"remaining_time":12.02095647},
{"learn":[0.3272045007],"iteration":505,"passed_time":12.29160924,"remaining_time":12.00010863},
{"learn":[0.3271417296],"iteration":506,"passed_time":12.3021796,"remaining_time":11.96247444},
{"learn":[0.3270684574],"iteration":507,"passed_time":12.33480306,"remaining_time":11.94630532},
{"learn":[0.3270302676],"iteration":508,"passed_time":12.34519374,"remaining_time":11.908625},
{"learn":[0.3269800336],"iteration":509,"passed_time":12.36407399,"remaining_time":11.87920834},
{"learn":[0.3269065043],"iteration":510,"passed_time":12.42223349,"remaining_time":11.88742109},
{"learn":[0.3267499517],"iteration":511,"passed_time":12.43090357,"remaining_time":11.84820496},
{"learn":[0.3265881056],"iteration":512,"passed_time":12.44848748,"remaining_time":11.81756998},
{"learn":[0.326398678],"iteration":513,"passed_time":12.46139696,"remaining_time":11.78256599},
{"learn":[0.3262632991],"iteration":514,"passed_time":12.49679576,"remaining_time":11.76882707},
{"learn":[0.32619157],"iteration":515,"passed_time":12.52049855,"remaining_time":11.74403352},
{"learn":[0.3261271273],"iteration":516,"passed_time":12.53965261,"remaining_time":11.71499461},
{"learn":[0.3260855728],"iteration":517,"passed_time":12.56308101,"remaining_time":11.68997114},
{"learn":[0.3260417895],"iteration":518,"passed_time":12.58478778,"remaining_time":11.66335823},
{"learn":[0.325995756],"iteration":519,"passed_time":12.62390306,"remaining_time":11.65283359},
{"learn":[0.3258993599],"iteration":520,"passed_time":12.6463165,"remaining_time":11.62684377},
{"learn":[0.3258239875],"iteration":521,"passed_time":12.65734285,"remaining_time":11.59044038},
{"learn":[0.3257759823],"iteration":522,"passed_time":12.67385123,"remaining_time":11.55913392},
{"learn":[0.3256720639],"iteration":523,"passed_time":12.7245675,"remaining_time":11.55895826},
{"learn":[0.3254782216],"iteration":524,"passed_time":12.77396672,"remaining_time":11.55739846},
{"learn":[0.3254096213],"iteration":525,"passed_time":12.80615352,"remaining_time":11.54014595},
{"learn":[0.3253597731],"iteration":526,"passed_time":12.81701093,"remaining_time":11.50369292},
{"learn":[0.3252860294],"iteration":527,"passed_time":12.82862614,"remaining_time":11.46801428},
{"learn":[0.3252141288],"iteration":528,"passed_time":12.85490784,"remaining_time":11.44548506},
{"learn":[0.3250412244],"iteration":529,"passed_time":12.8815885,"remaining_time":11.42329546},
{"learn":[0.3249249619],"iteration":530,"passed_time":12.89495065,"remaining_time":11.38932553},
{"learn":[0.3248794856],"iteration":531,"passed_time":12.92935409,"remaining_time":11.37394307},
{"learn":[0.3248169717],"iteration":532,"passed_time":12.94251413,"remaining_time":11.33987636},
{"learn":[0.3247924548],"iteration":533,"passed_time":12.94964244,"remaining_time":11.3006243},
{"learn":[0.3247142106],"iteration":534,"passed_time":12.97032118,"remaining_time":11.27326981},
{"learn":[0.3246641695],"iteration":535,"passed_time":12.99451326,"remaining_time":11.24898163},
{"learn":[0.324619679],"iteration":536,"passed_time":13.01422301,"remaining_time":11.22082915},
{"learn":[0.3245503929],"iteration":537,"passed_time":13.02833563,"remaining_time":11.1879016},
{"learn":[0.3244806783],"iteration":538,"passed_time":13.04941513,"remaining_time":11.16100255},
{"learn":[0.3244113279],"iteration":539,"passed_time":13.06578659,"remaining_time":11.13011451},
{"learn":[0.324326033],"iteration":540,"passed_time":13.07706904,"remaining_time":11.09496246},
{"learn":[0.3241301119],"iteration":541,"passed_time":13.09443078,"remaining_time":11.06503561},
{"learn":[0.3240352159],"iteration":542,"passed_time":13.11339664,"remaining_time":11.03650509},
{"learn":[0.3239838889],"iteration":543,"passed_time":13.14397058,"remaining_time":11.01774005},
{"learn":[0.323970066],"iteration":544,"passed_time":13.15243538,"remaining_time":10.98047357},
{"learn":[0.3239327334],"iteration":545,"passed_time":13.16239897,"remaining_time":10.94455885},
{"learn":[0.323892079],"iteration":546,"passed_time":13.20568091,"remaining_time":10.93633172},
{"learn":[0.3236193282],"iteration":547,"passed_time":13.23908996,"remaining_time":10.91983333},
{"learn":[0.323572716],"iteration":548,"passed_time":13.24959213,"remaining_time":10.88445547},
{"learn":[0.3235258467],"iteration":549,"passed_time":13.2602324,"remaining_time":10.84928106},
{"learn":[0.3234908286],"iteration":550,"passed_time":13.27601704,"remaining_time":10.81838775},
{"learn":[0.3233509278],"iteration":551,"passed_time":13.29364485,"remaining_time":10.78904509},
{"learn":[0.3232672402],"iteration":552,"passed_time":13.30470088,"remaining_time":10.75443272},
{"learn":[0.3231062728],"iteration":553,"passed_time":13.31559211,"remaining_time":10.71977271},
{"learn":[0.323054903],"iteration":554,"passed_time":13.35080323,"remaining_time":10.70469808},
{"learn":[0.3230195635],"iteration":555,"passed_time":13.37266934,"remaining_time":10.67889422},
{"learn":[0.322964679],"iteration":556,"passed_time":13.38453197,"remaining_time":10.64514841},
{"learn":[0.3228620893],"iteration":557,"passed_time":13.39926117,"remaining_time":10.61375168},
{"learn":[0.3228040545],"iteration":558,"passed_time":13.44283731,"remaining_time":10.60517219},
{"learn":[0.3227020007],"iteration":559,"passed_time":13.45517903,"remaining_time":10.57192638},
{"learn":[0.3226059903],"iteration":560,"passed_time":13.50092113,"remaining_time":10.56489194},
{"learn":[0.3225441836],"iteration":561,"passed_time":13.51248381,"remaining_time":10.53108169},
{"learn":[0.3225100228],"iteration":562,"passed_time":13.52919248,"remaining_time":10.50134478},
{"learn":[0.3224687898],"iteration":563,"passed_time":13.54537487,"remaining_time":10.47124724},
{"learn":[0.3222968927],"iteration":564,"passed_time":13.562562,"remaining_time":10.44197251},
{"learn":[0.3221227239],"iteration":565,"passed_time":13.59641477,"remaining_time":10.42551945},
{"learn":[0.3218413364],"iteration":566,"passed_time":13.6180766,"remaining_time":10.39969518},
{"learn":[0.3218028894],"iteration":567,"passed_time":13.64280539,"remaining_time":10.37621818},
{"learn":[0.3216415577],"iteration":568,"passed_time":13.67385301,"remaining_time":10.3575231},
{"learn":[0.3215343818],"iteration":569,"passed_time":13.68984203,"remaining_time":10.32742469},
{"learn":[0.3213595915],"iteration":570,"passed_time":13.70450442,"remaining_time":10.29637898},
{"learn":[0.3213259236],"iteration":571,"passed_time":13.72537356,"remaining_time":10.27003476},
{"learn":[0.3212060393],"iteration":572,"passed_time":13.75853954,"remaining_time":10.25287327},
{"learn":[0.3211531693],"iteration":573,"passed_time":13.77296172,"remaining_time":10.22174511},
{"learn":[0.3211205729],"iteration":574,"passed_time":13.78351341,"remaining_time":10.18781426},
{"learn":[0.3209593698],"iteration":575,"passed_time":13.82381823,"remaining_time":10.1758662},
{"learn":[0.32089497],"iteration":576,"passed_time":13.83938265,"remaining_time":10.1456826},
{"learn":[0.3208575945],"iteration":577,"passed_time":13.84586647,"remaining_time":10.10891981},
{"learn":[0.3208077249],"iteration":578,"passed_time":13.86776759,"remaining_time":10.08347177},
{"learn":[0.3207741641],"iteration":579,"passed_time":13.9074238,"remaining_time":10.0708931},
{"learn":[0.3206988345],"iteration":580,"passed_time":13.93836491,"remaining_time":10.05193614},
{"learn":[0.3205821219],"iteration":581,"passed_time":13.96444643,"remaining_time":10.02944778},
{"learn":[0.3205438464],"iteration":582,"passed_time":13.97652883,"remaining_time":9.996934},
{"learn":[0.3203397601],"iteration":583,"passed_time":13.98939999,"remaining_time":9.965052046},
{"learn":[0.3202825825],"iteration":584,"passed_time":14.01358261,"remaining_time":9.941259455},
{"learn":[0.3202296482],"iteration":585,"passed_time":14.04462492,"remaining_time":9.9223118},
{"learn":[0.3201838504],"iteration":586,"passed_time":14.06050678,"remaining_time":9.892656386},
{"learn":[0.3201474822],"iteration":587,"passed_time":14.08446898,"remaining_time":9.868709555},
{"learn":[0.3200662591],"iteration":588,"passed_time":14.09915211,"remaining_time":9.838287809},
{"learn":[0.320014525],"iteration":589,"passed_time":14.1339807,"remaining_time":9.82191879},
{"learn":[0.3199289729],"iteration":590,"passed_time":14.14491783,"remaining_time":9.788953286},
{"learn":[0.3198921547],"iteration":591,"passed_time":14.1563003,"remaining_time":9.756369122},
{"learn":[0.3195925723],"iteration":592,"passed_time":14.16767164,"remaining_time":9.723848831},
{"learn":[0.3193904148],"iteration":593,"passed_time":14.18479215,"remaining_time":9.695329316},
{"learn":[0.3193225218],"iteration":594,"passed_time":14.21778539,"remaining_time":9.67765224},
{"learn":[0.3192714734],"iteration":595,"passed_time":14.23476602,"remaining_time":9.649069586},
{"learn":[0.3191933793],"iteration":596,"passed_time":14.25654881,"remaining_time":9.623767458},
{"learn":[0.319121693],"iteration":597,"passed_time":14.27126868,"remaining_time":9.593729115},
{"learn":[0.3189963866],"iteration":598,"passed_time":14.27870973,"remaining_time":9.558869118},
{"learn":[0.3188404769],"iteration":599,"passed_time":14.31421974,"remaining_time":9.542813161},
{"learn":[0.3187160706],"iteration":600,"passed_time":14.33191101,"remaining_time":9.51486272},
{"learn":[0.3186134381],"iteration":601,"passed_time":14.35049325,"remaining_time":9.487535406},
{"learn":[0.3185721622],"iteration":602,"passed_time":14.37190181,"remaining_time":9.462097874},
{"learn":[0.3185275003],"iteration":603,"passed_time":14.38309478,"remaining_time":9.42997605},
{"learn":[0.318350524],"iteration":604,"passed_time":14.40328782,"remaining_time":9.403799488},
{"learn":[0.3182247891],"iteration":605,"passed_time":14.4306846,"remaining_time":9.382326294},
{"learn":[0.3180387047],"iteration":606,"passed_time":14.44885901,"remaining_time":9.354862585},
{"learn":[0.3179403155],"iteration":607,"passed_time":14.48022312,"remaining_time":9.335933329},
{"learn":[0.3178730654],"iteration":608,"passed_time":14.53158707,"remaining_time":9.329803849},
{"learn":[0.3177636822],"iteration":609,"passed_time":14.57068309,"remaining_time":9.315682634},
{"learn":[0.3176360827],"iteration":610,"passed_time":14.59974581,"remaining_time":9.29509185},
{"learn":[0.3175325501],"iteration":611,"passed_time":14.6127559,"remaining_time":9.264296222},
{"learn":[0.3174584849],"iteration":612,"passed_time":14.63105258,"remaining_time":9.236896161},
{"learn":[0.3173639748],"iteration":613,"passed_time":14.64936714,"remaining_time":9.209536996},
{"learn":[0.3173319356],"iteration":614,"passed_time":14.67234683,"remaining_time":9.185127688},
{"learn":[0.317114755],"iteration":615,"passed_time":14.68726891,"remaining_time":9.155700097},
{"learn":[0.3170669641],"iteration":616,"passed_time":14.69542673,"remaining_time":9.122120644},
{"learn":[0.3169017749],"iteration":617,"passed_time":14.74319807,"remaining_time":9.113109487},
{"learn":[0.3166914522],"iteration":618,"passed_time":14.77094424,"remaining_time":9.091647422},
{"learn":[0.3166627562],"iteration":619,"passed_time":14.81588524,"remaining_time":9.08070386},
{"learn":[0.3165747396],"iteration":620,"passed_time":14.85278059,"remaining_time":9.064740489},
{"learn":[0.3165348782],"iteration":621,"passed_time":14.86131479,"remaining_time":9.03147426},
{"learn":[0.3164858443],"iteration":622,"passed_time":14.87469583,"remaining_time":9.001220432},
{"learn":[0.3164440326],"iteration":623,"passed_time":14.90899754,"remaining_time":8.983626721},
{"learn":[0.3164019638],"iteration":624,"passed_time":14.92425291,"remaining_time":8.954551747},
{"learn":[0.3163721749],"iteration":625,"passed_time":14.94220212,"remaining_time":8.927130338},
{"learn":[0.316331842],"iteration":626,"passed_time":14.95211907,"remaining_time":8.894960787},
{"learn":[0.3163247055],"iteration":627,"passed_time":14.95705167,"remaining_time":8.859909586},
{"learn":[0.3162503618],"iteration":628,"passed_time":14.97267233,"remaining_time":8.831258242},
{"learn":[0.3161959702],"iteration":629,"passed_time":14.99692506,"remaining_time":8.807717895},
{"learn":[0.3160255089],"iteration":630,"passed_time":15.01328617,"remaining_time":8.779560374},
{"learn":[0.3159523439],"iteration":631,"passed_time":15.02940456,"remaining_time":8.751298859},
{"learn":[0.3157902835],"iteration":632,"passed_time":15.05976191,"remaining_time":8.731331153},
{"learn":[0.3156810075],"iteration":633,"passed_time":15.07216572,"remaining_time":8.700966333},
{"learn":[0.3156407817],"iteration":634,"passed_time":15.08055565,"remaining_time":8.668350887},
{"learn":[0.3156040492],"iteration":635,"passed_time":15.09313375,"remaining_time":8.638208624},
{"learn":[0.3155571155],"iteration":636,"passed_time":15.12554365,"remaining_time":8.619422836},
{"learn":[0.3154997665],"iteration":637,"passed_time":15.13780744,"remaining_time":8.58916347},
{"learn":[0.3154565833],"iteration":638,"passed_time":15.15814795,"remaining_time":8.563523332},
{"learn":[0.3153986984],"iteration":639,"passed_time":15.16914818,"remaining_time":8.532645853},
{"learn":[0.3153433639],"iteration":640,"passed_time":15.19297682,"remaining_time":8.5090151},
{"learn":[0.3153189327],"iteration":641,"passed_time":15.20622622,"remaining_time":8.479484403},
{"learn":[0.3152141357],"iteration":642,"passed_time":15.22220363,"remaining_time":8.45151897},
{"learn":[0.3151027379],"iteration":643,"passed_time":15.23143638,"remaining_time":8.419862345},
{"learn":[0.3150622979],"iteration":644,"passed_time":15.24361888,"remaining_time":8.389898764},
{"learn":[0.3150014556],"iteration":645,"passed_time":15.2664582,"remaining_time":8.365830034},
{"learn":[0.3149779245],"iteration":646,"passed_time":15.27837459,"remaining_time":8.33580561},
{"learn":[0.3149586581],"iteration":647,"passed_time":15.29644795,"remaining_time":8.309181601},
{"learn":[0.3149178108],"iteration":648,"passed_time":15.3086174,"remaining_time":8.279390922},
{"learn":[0.314875292],"iteration":649,"passed_time":15.3600204,"remaining_time":8.270780215},
{"learn":[0.3147925902],"iteration":650,"passed_time":15.37296965,"remaining_time":8.241423051},
{"learn":[0.3147580865],"iteration":651,"passed_time":15.38654117,"remaining_time":8.212448356},
{"learn":[0.3146930009],"iteration":652,"passed_time":15.40385509,"remaining_time":8.185509517},
{"learn":[0.3146203288],"iteration":653,"passed_time":15.4213647,"remaining_time":8.158703651},
{"learn":[0.314556079],"iteration":654,"passed_time":15.43765642,"remaining_time":8.131284679},
{"learn":[0.3145296975],"iteration":655,"passed_time":15.46111,"remaining_time":8.107655241},
{"learn":[0.3145081166],"iteration":656,"passed_time":15.48697797,"remaining_time":8.085286825},
{"learn":[0.3144372019],"iteration":657,"passed_time":15.50642941,"remaining_time":8.059572731},
{"learn":[0.314323511],"iteration":658,"passed_time":15.5395194,"remaining_time":8.040934922},
{"learn":[0.3142420951],"iteration":659,"passed_time":15.55388492,"remaining_time":8.012607384},
{"learn":[0.3141796026],"iteration":660,"passed_time":15.57167571,"remaining_time":7.986078766},
{"learn":[0.3140555392],"iteration":661,"passed_time":15.58023335,"remaining_time":7.954862343},
{"learn":[0.3140171351],"iteration":662,"passed_time":15.59091034,"remaining_time":7.924791531},
{"learn":[0.3137254608],"iteration":663,"passed_time":15.61062547,"remaining_time":7.899352649},
{"learn":[0.313480763],"iteration":664,"passed_time":15.62313601,"remaining_time":7.8703016},
{"learn":[0.3133560352],"iteration":665,"passed_time":15.63930373,"remaining_time":7.843134301},
{"learn":[0.3133285608],"iteration":666,"passed_time":15.67669978,"remaining_time":7.826598243},
{"learn":[0.3132813272],"iteration":667,"passed_time":15.68869888,"remaining_time":7.797377287},
{"learn":[0.3130025328],"iteration":668,"passed_time":15.70697409,"remaining_time":7.77131304},
{"learn":[0.3129590067],"iteration":669,"passed_time":15.7240063,"remaining_time":7.74465982},
{"learn":[0.312883077],"iteration":670,"passed_time":15.7337412,"remaining_time":7.714457309},
{"learn":[0.3128064616],"iteration":671,"passed_time":15.76697486,"remaining_time":7.695785349},
{"learn":[0.3127073652],"iteration":672,"passed_time":15.78777764,"remaining_time":7.671030146},
{"learn":[0.3126423439],"iteration":673,"passed_time":15.82447372,"remaining_time":7.653973938},
{"learn":[0.3124829839],"iteration":674,"passed_time":15.83433833,"remaining_time":7.623940679},
{"learn":[0.3124506232],"iteration":675,"passed_time":15.84907508,"remaining_time":7.596302257},
{"learn":[0.3124146408],"iteration":676,"passed_time":15.85782899,"remaining_time":7.56584751},
{"learn":[0.3123919241],"iteration":677,"passed_time":15.86274248,"remaining_time":7.533632859},
{"learn":[0.3123229166],"iteration":678,"passed_time":15.8886701,"remaining_time":7.511433142},
{"learn":[0.3122382861],"iteration":679,"passed_time":15.91046816,"remaining_time":7.487279133},
{"learn":[0.3122089472],"iteration":680,"passed_time":15.92326456,"remaining_time":7.458915412},
{"learn":[0.3121882664],"iteration":681,"passed_time":15.93943413,"remaining_time":7.432170167},
{"learn":[0.3121481906],"iteration":682,"passed_time":15.98260479,"remaining_time":7.417987874},
{"learn":[0.3121145013],"iteration":683,"passed_time":15.99232362,"remaining_time":7.38826647},
{"learn":[0.3120658532],"iteration":684,"passed_time":16.00860842,"remaining_time":7.361622849},
{"learn":[0.3120385074],"iteration":685,"passed_time":16.02504243,"remaining_time":7.335077729},
{"learn":[0.3119917023],"iteration":686,"passed_time":16.05506539,"remaining_time":7.314753228},
{"learn":[0.3119074789],"iteration":687,"passed_time":16.08717593,"remaining_time":7.295347226},
{"learn":[0.3118582522],"iteration":688,"passed_time":16.09986448,"remaining_time":7.267137667},
{"learn":[0.3118194194],"iteration":689,"passed_time":16.11615845,"remaining_time":7.240592928},
{"learn":[0.3117793651],"iteration":690,"passed_time":16.13070258,"remaining_time":7.213295365},
{"learn":[0.3117371034],"iteration":691,"passed_time":16.14122768,"remaining_time":7.184245847},
{"learn":[0.3117034998],"iteration":692,"passed_time":16.17023904,"remaining_time":7.163439227},
{"learn":[0.3116744395],"iteration":693,"passed_time":16.18713864,"remaining_time":7.13726862},
{"learn":[0.3115231803],"iteration":694,"passed_time":16.21770138,"remaining_time":7.117120748},
{"learn":[0.3113882086],"iteration":695,"passed_time":16.23679797,"remaining_time":7.091934743},
{"learn":[0.3113468256],"iteration":696,"passed_time":16.25044553,"remaining_time":7.06439741},
{"learn":[0.3113184082],"iteration":697,"passed_time":16.26088047,"remaining_time":7.035509889},
{"learn":[0.311278011],"iteration":698,"passed_time":16.28263308,"remaining_time":7.011548724},
{"learn":[0.3109200938],"iteration":699,"passed_time":16.29593053,"remaining_time":6.983970227},
{"learn":[0.3108631948],"iteration":700,"passed_time":16.30593985,"remaining_time":6.95502998},
{"learn":[0.3108173113],"iteration":701,"passed_time":16.34289754,"remaining_time":6.937583287},
{"learn":[0.3107818646],"iteration":702,"passed_time":16.36235476,"remaining_time":6.912687575},
{"learn":[0.3107209795],"iteration":703,"passed_time":16.37587189,"remaining_time":6.885309771},
{"learn":[0.3106735958],"iteration":704,"passed_time":16.38945313,"remaining_time":6.857998118},
{"learn":[0.3105281444],"iteration":705,"passed_time":16.41615191,"remaining_time":6.836187907},
{"learn":[0.3104878972],"iteration":706,"passed_time":16.44262029,"remaining_time":6.814268379},
{"learn":[0.3104438567],"iteration":707,"passed_time":16.45538313,"remaining_time":6.786683436},
{"learn":[0.310281132],"iteration":708,"passed_time":16.4980199,"remaining_time":6.771401679},
{"learn":[0.3101602619],"iteration":709,"passed_time":16.51232418,"remaining_time":6.744470441},
{"learn":[0.3101175287],"iteration":710,"passed_time":16.52461282,"remaining_time":6.71675542},
{"learn":[0.3100431635],"iteration":711,"passed_time":16.55445885,"remaining_time":6.696185601},
{"learn":[0.3099986301],"iteration":712,"passed_time":16.57711126,"remaining_time":6.672694155},
{"learn":[0.3099710915],"iteration":713,"passed_time":16.58977695,"remaining_time":6.645204774},
{"learn":[0.3099231506],"iteration":714,"passed_time":16.5964278,"remaining_time":6.615359331},
{"learn":[0.3098864609],"iteration":715,"passed_time":16.62095484,"remaining_time":6.59266924},
{"learn":[0.3098552147],"iteration":716,"passed_time":16.65272221,"remaining_time":6.57283178},
{"learn":[0.3098125029],"iteration":717,"passed_time":16.69984167,"remaining_time":6.558990739},
{"learn":[0.3096777241],"iteration":718,"passed_time":16.71394224,"remaining_time":6.532152671},
{"learn":[0.3096392771],"iteration":719,"passed_time":16.72677085,"remaining_time":6.504855332},
{"learn":[0.3095969939],"iteration":720,"passed_time":16.73528687,"remaining_time":6.475929314},
{"learn":[0.3095555252],"iteration":721,"passed_time":16.74289203,"remaining_time":6.446709119},
{"learn":[0.3095150423],"iteration":722,"passed_time":16.76016277,"remaining_time":6.421251848},
{"learn":[0.3093768773],"iteration":723,"passed_time":16.80128687,"remaining_time":6.404910466},
{"learn":[0.3093448382],"iteration":724,"passed_time":16.81259187,"remaining_time":6.377190018},
{"learn":[0.3091644973],"iteration":725,"passed_time":16.82343627,"remaining_time":6.349340962},
{"learn":[0.3091392731],"iteration":726,"passed_time":16.84680485,"remaining_time":6.32624171},
{"learn":[0.3089999081],"iteration":727,"passed_time":16.85681809,"remaining_time":6.298151815},
{"learn":[0.308941016],"iteration":728,"passed_time":16.87358533,"remaining_time":6.272622255},
{"learn":[0.3088993115],"iteration":729,"passed_time":16.88966554,"remaining_time":6.246862595},
{"learn":[0.3088580785],"iteration":730,"passed_time":16.93302184,"remaining_time":6.231166724},
{"learn":[0.308822889],"iteration":731,"passed_time":16.94817585,"remaining_time":6.205069846},
{"learn":[0.3087675973],"iteration":732,"passed_time":16.95821175,"remaining_time":6.177138523},
{"learn":[0.308616381],"iteration":733,"passed_time":16.97061594,"remaining_time":6.150114224},
{"learn":[0.3085769482],"iteration":734,"passed_time":16.98568619,"remaining_time":6.12409094},
{"learn":[0.3085441161],"iteration":735,"passed_time":17.01007565,"remaining_time":6.101440177},
{"learn":[0.3085092052],"iteration":736,"passed_time":17.03794796,"remaining_time":6.080027563},
{"learn":[0.3084425337],"iteration":737,"passed_time":17.05600059,"remaining_time":6.055111322},
{"learn":[0.3084142021],"iteration":738,"passed_time":17.07119173,"remaining_time":6.029203032},
{"learn":[0.3083906281],"iteration":739,"passed_time":17.1016128,"remaining_time":6.008674768},
{"learn":[0.3083779196],"iteration":740,"passed_time":17.10875116,"remaining_time":5.979981851},
{"learn":[0.3083400726],"iteration":741,"passed_time":17.11724822,"remaining_time":5.951819462},
{"learn":[0.3082895172],"iteration":742,"passed_time":17.12831673,"remaining_time":5.924599461},
{"learn":[0.308071908],"iteration":743,"passed_time":17.13657301,"remaining_time":5.89645523},
{"learn":[0.3080284462],"iteration":744,"passed_time":17.15532164,"remaining_time":5.871955727},
{"learn":[0.307978405],"iteration":745,"passed_time":17.17485693,"remaining_time":5.847739492},
{"learn":[0.3077113977],"iteration":746,"passed_time":17.22016498,"remaining_time":5.832264711},
{"learn":[0.3076694146],"iteration":747,"passed_time":17.23150489,"remaining_time":5.805266354},
{"learn":[0.3075927134],"iteration":748,"passed_time":17.24750693,"remaining_time":5.779872148},
{"learn":[0.307546337],"iteration":749,"passed_time":17.25725783,"remaining_time":5.752419275},
{"learn":[0.3074645567],"iteration":750,"passed_time":17.26996263,"remaining_time":5.725992935},
{"learn":[0.307416873],"iteration":751,"passed_time":17.28669077,"remaining_time":5.700929936},
{"learn":[0.3073784903],"iteration":752,"passed_time":17.31447829,"remaining_time":5.679516783},
{"learn":[0.307277508],"iteration":753,"passed_time":17.33438146,"remaining_time":5.655514375},
{"learn":[0.3072271883],"iteration":754,"passed_time":17.34118244,"remaining_time":5.627271122},
{"learn":[0.3070541768],"iteration":755,"passed_time":17.35141611,"remaining_time":5.600192503},
{"learn":[0.3069078038],"iteration":756,"passed_time":17.38205468,"remaining_time":5.579708438},
{"learn":[0.306758302],"iteration":757,"passed_time":17.39942586,"remaining_time":5.554961818},
{"learn":[0.3067088181],"iteration":758,"passed_time":17.41055127,"remaining_time":5.528251457},
{"learn":[0.3066484901],"iteration":759,"passed_time":17.41758032,"remaining_time":5.500288521},
{"learn":[0.3066060356],"iteration":760,"passed_time":17.43404074,"remaining_time":5.475342624},
{"learn":[0.3065717033],"iteration":761,"passed_time":17.48579827,"remaining_time":5.461443553},
{"learn":[0.3064760572],"iteration":762,"passed_time":17.497574,"remaining_time":5.435026263},
{"learn":[0.3064168009],"iteration":763,"passed_time":17.50773635,"remaining_time":5.408148925},
{"learn":[0.3062463825],"iteration":764,"passed_time":17.53177668,"remaining_time":5.385578458},
{"learn":[0.3060877511],"iteration":765,"passed_time":17.55173256,"remaining_time":5.361756423},
{"learn":[0.3060460466],"iteration":766,"passed_time":17.56403472,"remaining_time":5.335619412},
{"learn":[0.3060137931],"iteration":767,"passed_time":17.57689369,"remaining_time":5.309686635},
{"learn":[0.3059698169],"iteration":768,"passed_time":17.60543955,"remaining_time":5.288500048},
{"learn":[0.3059035741],"iteration":769,"passed_time":17.63883133,"remaining_time":5.268741827},
{"learn":[0.305833838],"iteration":770,"passed_time":17.65057175,"remaining_time":5.242517421},
{"learn":[0.3057940622],"iteration":771,"passed_time":17.66539173,"remaining_time":5.217240043},
{"learn":[0.3057527649],"iteration":772,"passed_time":17.69239109,"remaining_time":5.195566335},
{"learn":[0.3057081673],"iteration":773,"passed_time":17.70371456,"remaining_time":5.169301669},
{"learn":[0.3055434495],"iteration":774,"passed_time":17.72120787,"remaining_time":5.1448668},
{"learn":[0.3053438851],"iteration":775,"passed_time":17.74962739,"remaining_time":5.123603783},
{"learn":[0.3053044308],"iteration":776,"passed_time":17.76087395,"remaining_time":5.097393681},
{"learn":[0.305182832],"iteration":777,"passed_time":17.78152819,"remaining_time":5.0739065},
{"learn":[0.3051411489],"iteration":778,"passed_time":17.79970049,"remaining_time":5.049722474},
{"learn":[0.3051010303],"iteration":779,"passed_time":17.81913933,"remaining_time":5.025911093},
{"learn":[0.3050652408],"iteration":780,"passed_time":17.83234963,"remaining_time":5.000364364},
{"learn":[0.3050191644],"iteration":781,"passed_time":17.83947332,"remaining_time":4.973152409},
{"learn":[0.3049793029],"iteration":782,"passed_time":17.85932899,"remaining_time":4.949520295},
{"learn":[0.3049488925],"iteration":783,"passed_time":17.87702789,"remaining_time":4.925303602},
{"learn":[0.3049066951],"iteration":784,"passed_time":17.90225702,"remaining_time":4.903165935},
{"learn":[0.3048648191],"iteration":785,"passed_time":17.91405139,"remaining_time":4.877362591},
{"learn":[0.3046820137],"iteration":786,"passed_time":17.95204635,"remaining_time":4.858685987},
{"learn":[0.3046017765],"iteration":787,"passed_time":17.97105204,"remaining_time":4.834851565},
{"learn":[0.3045533855],"iteration":788,"passed_time":17.98236462,"remaining_time":4.808972033},
{"learn":[0.3045111024],"iteration":789,"passed_time":17.99432313,"remaining_time":4.783301085},
{"learn":[0.3044573323],"iteration":790,"passed_time":18.00660618,"remaining_time":4.757750557},
{"learn":[0.3044067983],"iteration":791,"passed_time":18.01704946,"remaining_time":4.731750363},
{"learn":[0.3043441987],"iteration":792,"passed_time":18.04069784,"remaining_time":4.709236384},
{"learn":[0.3042491741],"iteration":793,"passed_time":18.07090966,"remaining_time":4.688422405},
{"learn":[0.3041519208],"iteration":794,"passed_time":18.08899257,"remaining_time":4.664457203},
{"learn":[0.3041100877],"iteration":795,"passed_time":18.09965209,"remaining_time":4.638604304},
{"learn":[0.3040698191],"iteration":796,"passed_time":18.11116188,"remaining_time":4.6130061},
{"learn":[0.3039973613],"iteration":797,"passed_time":18.12138435,"remaining_time":4.587117342},
{"learn":[0.303943634],"iteration":798,"passed_time":18.13418264,"remaining_time":4.561915784},
{"learn":[0.3039024867],"iteration":799,"passed_time":18.16966844,"remaining_time":4.54241711},
{"learn":[0.3038669115],"iteration":800,"passed_time":18.18356072,"remaining_time":4.517513837},
{"learn":[0.303825357],"iteration":801,"passed_time":18.19711025,"remaining_time":4.492553402},
{"learn":[0.3036090551],"iteration":802,"passed_time":18.22469215,"remaining_time":4.471063953},
{"learn":[0.3035603855],"iteration":803,"passed_time":18.24275703,"remaining_time":4.447239276},
{"learn":[0.3035273391],"iteration":804,"passed_time":18.2755269,"remaining_time":4.426990989},
{"learn":[0.3034874348],"iteration":805,"passed_time":18.28468389,"remaining_time":4.401028132},
{"learn":[0.3032314429],"iteration":806,"passed_time":18.29079107,"remaining_time":4.374377542},
{"learn":[0.3032006682],"iteration":807,"passed_time":18.30377713,"remaining_time":4.349412388},
{"learn":[0.3031572492],"iteration":808,"passed_time":18.34444663,"remaining_time":4.33101274},
{"learn":[0.3030778263],"iteration":809,"passed_time":18.36653847,"remaining_time":4.308200383},
{"learn":[0.3030429797],"iteration":810,"passed_time":18.38405903,"remaining_time":4.284324484},
{"learn":[0.3030019824],"iteration":811,"passed_time":18.43545143,"remaining_time":4.268306489},
{"learn":[0.3029681002],"iteration":812,"passed_time":18.45401401,"remaining_time":4.244650208},
{"learn":[0.3029257099],"iteration":813,"passed_time":18.46743307,"remaining_time":4.219831143},
{"learn":[0.3028931136],"iteration":814,"passed_time":18.47735745,"remaining_time":4.194246782},
{"learn":[0.3028546023],"iteration":815,"passed_time":18.49960087,"remaining_time":4.171478627},
{"learn":[0.3028108404],"iteration":816,"passed_time":18.54080282,"remaining_time":4.152958281},
{"learn":[0.3026422651],"iteration":817,"passed_time":18.55563313,"remaining_time":4.128514951},
{"learn":[0.3025992318],"iteration":818,"passed_time":18.57641656,"remaining_time":4.105410741},
{"learn":[0.3025448403],"iteration":819,"passed_time":18.59294442,"remaining_time":4.081378044},
{"learn":[0.3025073791],"iteration":820,"passed_time":18.59927403,"remaining_time":4.055140136},
{"learn":[0.3024660175],"iteration":821,"passed_time":18.60727265,"remaining_time":4.029312082},
{"learn":[0.3024338926],"iteration":822,"passed_time":18.62277221,"remaining_time":4.00514056},
{"learn":[0.3023604489],"iteration":823,"passed_time":18.6395692,"remaining_time":3.981267208},
{"learn":[0.3023211233],"iteration":824,"passed_time":18.64758626,"remaining_time":3.9555486},
{"learn":[0.3022852265],"iteration":825,"passed_time":18.67412718,"remaining_time":3.933774974},
{"learn":[0.3022491798],"iteration":826,"passed_time":18.69524947,"remaining_time":3.910856298},
{"learn":[0.3022213411],"iteration":827,"passed_time":18.70346191,"remaining_time":3.885260204},
{"learn":[0.3021831084],"iteration":828,"passed_time":18.71464149,"remaining_time":3.860318089},
{"learn":[0.3021459901],"iteration":829,"passed_time":18.72764142,"remaining_time":3.835781978},
{"learn":[0.3021023782],"iteration":830,"passed_time":18.74122596,"remaining_time":3.811392523},
{"learn":[0.3020653028],"iteration":831,"passed_time":18.78133095,"remaining_time":3.792384135},
{"learn":[0.3020226768],"iteration":832,"passed_time":18.81912277,"remaining_time":3.772861347},
{"learn":[0.3019776505],"iteration":833,"passed_time":18.84608372,"remaining_time":3.751138967},
{"learn":[0.3019195299],"iteration":834,"passed_time":18.8625824,"remaining_time":3.727336642},
{"learn":[0.3018863549],"iteration":835,"passed_time":18.88223108,"remaining_time":3.704169733},
{"learn":[0.3018363138],"iteration":836,"passed_time":18.89525167,"remaining_time":3.679720456},
{"learn":[0.3017676278],"iteration":837,"passed_time":18.91598516,"remaining_time":3.656789495},
{"learn":[0.3017261377],"iteration":838,"passed_time":18.93434859,"remaining_time":3.633408966},
{"learn":[0.3016883979],"iteration":839,"passed_time":18.95826057,"remaining_time":3.611097251},
{"learn":[0.3016466291],"iteration":840,"passed_time":18.96594402,"remaining_time":3.585713554},
{"learn":[0.3016058032],"iteration":841,"passed_time":18.97721836,"remaining_time":3.561045726},
{"learn":[0.3015551621],"iteration":842,"passed_time":18.99896949,"remaining_time":3.538360865},
{"learn":[0.3015151292],"iteration":843,"passed_time":19.02573748,"remaining_time":3.516605506},
{"learn":[0.3014650238],"iteration":844,"passed_time":19.04490973,"remaining_time":3.493444981},
{"learn":[0.3014233193],"iteration":845,"passed_time":19.07674576,"remaining_time":3.472599111},
{"learn":[0.3013556405],"iteration":846,"passed_time":19.09150136,"remaining_time":3.448641922},
{"learn":[0.301321094],"iteration":847,"passed_time":19.10564954,"remaining_time":3.424597559},
{"learn":[0.301287426],"iteration":848,"passed_time":19.1163687,"remaining_time":3.399966636},
{"learn":[0.3012504149],"iteration":849,"passed_time":19.12882393,"remaining_time":3.375674812},
{"learn":[0.3012227262],"iteration":850,"passed_time":19.15073637,"remaining_time":3.353066651},
{"learn":[0.3011832934],"iteration":851,"passed_time":19.18610546,"remaining_time":3.332797663},
{"learn":[0.3011025847],"iteration":852,"passed_time":19.22161343,"remaining_time":3.312517203},
{"learn":[0.3010618446],"iteration":853,"passed_time":19.23407085,"remaining_time":3.288260357},
{"learn":[0.3010296339],"iteration":854,"passed_time":19.24232324,"remaining_time":3.263317977},
{"learn":[0.3009875437],"iteration":855,"passed_time":19.26192715,"remaining_time":3.240324193},
{"learn":[0.3009537258],"iteration":856,"passed_time":19.28027614,"remaining_time":3.217128924},
{"learn":[0.30091395],"iteration":857,"passed_time":19.30975579,"remaining_time":3.19578709},
{"learn":[0.3008699953],"iteration":858,"passed_time":19.32657841,"remaining_time":3.172348727},
{"learn":[0.3008379775],"iteration":859,"passed_time":19.35137158,"remaining_time":3.150223281},
{"learn":[0.3007992948],"iteration":860,"passed_time":19.38397217,"remaining_time":3.129352069},
{"learn":[0.3007657769],"iteration":861,"passed_time":19.3946714,"remaining_time":3.104947393},
{"learn":[0.3007306731],"iteration":862,"passed_time":19.41274905,"remaining_time":3.081745794},
{"learn":[0.3006909617],"iteration":863,"passed_time":19.43862291,"remaining_time":3.059783236},
{"learn":[0.3006518289],"iteration":864,"passed_time":19.45785365,"remaining_time":3.036774848},
{"learn":[0.3006044881],"iteration":865,"passed_time":19.48003838,"remaining_time":3.014232266},
{"learn":[0.300564198],"iteration":866,"passed_time":19.48947789,"remaining_time":2.989735362},
{"learn":[0.3005185931],"iteration":867,"passed_time":19.50093561,"remaining_time":2.965580069},
{"learn":[0.3004856753],"iteration":868,"passed_time":19.5243353,"remaining_time":2.943254228},
{"learn":[0.3004479998],"iteration":869,"passed_time":19.53592064,"remaining_time":2.919160556},
{"learn":[0.3004208254],"iteration":870,"passed_time":19.55100464,"remaining_time":2.895613776},
{"learn":[0.3003773207],"iteration":871,"passed_time":19.58927079,"remaining_time":2.875489291},
{"learn":[0.3003545182],"iteration":872,"passed_time":19.60046379,"remaining_time":2.851384766},
{"learn":[0.3003186429],"iteration":873,"passed_time":19.60888604,"remaining_time":2.826910344},
{"learn":[0.3002854251],"iteration":874,"passed_time":19.62419387,"remaining_time":2.803456266},
{"learn":[0.300255379],"iteration":875,"passed_time":19.64764838,"remaining_time":2.781173972},
{"learn":[0.3002177463],"iteration":876,"passed_time":19.65768982,"remaining_time":2.757007809},
{"learn":[0.3001985871],"iteration":877,"passed_time":19.66485459,"remaining_time":2.7324741},
{"learn":[0.3001048056],"iteration":878,"passed_time":19.67346519,"remaining_time":2.70817894},
{"learn":[0.3000742023],"iteration":879,"passed_time":19.68460864,"remaining_time":2.684264814},
{"learn":[0.300007938],"iteration":880,"passed_time":19.71681337,"remaining_time":2.663224507},
{"learn":[0.2999769061],"iteration":881,"passed_time":19.77312258,"remaining_time":2.645383747},
{"learn":[0.2999408808],"iteration":882,"passed_time":19.80785103,"remaining_time":2.624596343},
{"learn":[0.2999012551],"iteration":883,"passed_time":19.8216861,"remaining_time":2.601035732},
{"learn":[0.299865144],"iteration":884,"passed_time":19.83625009,"remaining_time":2.577591819},
{"learn":[0.2998260112],"iteration":885,"passed_time":19.84588268,"remaining_time":2.553533437},
{"learn":[0.2997614614],"iteration":886,"passed_time":19.86370502,"remaining_time":2.530550922},
{"learn":[0.299730751],"iteration":887,"passed_time":19.89055046,"remaining_time":2.508718076},
{"learn":[0.2996885964],"iteration":888,"passed_time":19.91051414,"remaining_time":2.486014701},
{"learn":[0.2996624507],"iteration":889,"passed_time":19.92457326,"remaining_time":2.462587706},
{"learn":[0.2996253539],"iteration":890,"passed_time":19.94010609,"remaining_time":2.439362025},
{"learn":[0.2995872069],"iteration":891,"passed_time":20.00442864,"remaining_time":2.422060867},
{"learn":[0.2995483313],"iteration":892,"passed_time":20.03792208,"remaining_time":2.400960428},
{"learn":[0.2995076555],"iteration":893,"passed_time":20.09151665,"remaining_time":2.38221562},
{"learn":[0.2993748697],"iteration":894,"passed_time":20.11441154,"remaining_time":2.359791298},
{"learn":[0.2993458951],"iteration":895,"passed_time":20.12871436,"remaining_time":2.336368631},
{"learn":[0.2993173706],"iteration":896,"passed_time":20.14301446,"remaining_time":2.312965986},
{"learn":[0.299274316],"iteration":897,"passed_time":20.20418978,"remaining_time":2.29490797},
{"learn":[0.2992379264],"iteration":898,"passed_time":20.22113558,"remaining_time":2.271784976},
{"learn":[0.2992011295],"iteration":899,"passed_time":20.23424053,"remaining_time":2.248248947},
{"learn":[0.2991600037],"iteration":900,"passed_time":20.24105184,"remaining_time":2.224044542},
{"learn":[0.2991237855],"iteration":901,"passed_time":20.25403241,"remaining_time":2.200548976},
{"learn":[0.2990851242],"iteration":902,"passed_time":20.38058485,"remaining_time":2.189276557},
{"learn":[0.29904672],"iteration":903,"passed_time":20.55445392,"remaining_time":2.182773868},
{"learn":[0.2990082301],"iteration":904,"passed_time":20.56923469,"remaining_time":2.159201432},
{"learn":[0.2989659256],"iteration":905,"passed_time":20.59960924,"remaining_time":2.137266301},
{"learn":[0.298929193],"iteration":906,"passed_time":20.62724809,"remaining_time":2.115032053},
{"learn":[0.2988945607],"iteration":907,"passed_time":20.6817463,"remaining_time":2.095507334},
{"learn":[0.2988523205],"iteration":908,"passed_time":20.70129801,"remaining_time":2.072407172},
{"learn":[0.2988174524],"iteration":909,"passed_time":20.70887129,"remaining_time":2.048130128},
{"learn":[0.2987830344],"iteration":910,"passed_time":20.72388451,"remaining_time":2.024616598},
{"learn":[0.2987438373],"iteration":911,"passed_time":20.80346085,"remaining_time":2.007351486},
{"learn":[0.2987140484],"iteration":912,"passed_time":20.81215348,"remaining_time":1.983195348},
{"learn":[0.2986770801],"iteration":913,"passed_time":20.83302924,"remaining_time":1.960219382},
{"learn":[0.2986477198],"iteration":914,"passed_time":20.86504396,"remaining_time":1.938282772},
{"learn":[0.2986163021],"iteration":915,"passed_time":20.87974837,"remaining_time":1.91473675},
{"learn":[0.2985790553],"iteration":916,"passed_time":20.90325003,"remaining_time":1.892006273},
{"learn":[0.2985277497],"iteration":917,"passed_time":20.93547138,"remaining_time":1.870052999},
{"learn":[0.2982963176],"iteration":918,"passed_time":21.01009608,"remaining_time":1.851814779},
{"learn":[0.2982584278],"iteration":919,"passed_time":21.01948496,"remaining_time":1.827781301},
{"learn":[0.2982189307],"iteration":920,"passed_time":21.03991223,"remaining_time":1.804726457},
{"learn":[0.29818567],"iteration":921,"passed_time":21.08728009,"remaining_time":1.78395645},
{"learn":[0.2981523878],"iteration":922,"passed_time":21.13918711,"remaining_time":1.763507483},
{"learn":[0.2981222774],"iteration":923,"passed_time":21.14803373,"remaining_time":1.739448661},
{"learn":[0.2980911598],"iteration":924,"passed_time":21.16488196,"remaining_time":1.71607151},
{"learn":[0.2980518127],"iteration":925,"passed_time":21.25105664,"remaining_time":1.698248587},
{"learn":[0.2980192806],"iteration":926,"passed_time":21.27687498,"remaining_time":1.675525214},
{"learn":[0.2979835767],"iteration":927,"passed_time":21.31640396,"remaining_time":1.653858928},
{"learn":[0.2979477443],"iteration":928,"passed_time":21.3575204,"remaining_time":1.632275509},
{"learn":[0.2979046254],"iteration":929,"passed_time":21.3933197,"remaining_time":1.61024987},
{"learn":[0.2978679786],"iteration":930,"passed_time":21.42741402,"remaining_time":1.588068279},
{"learn":[0.2978355536],"iteration":931,"passed_time":21.50119045,"remaining_time":1.568756385},
{"learn":[0.2978021],"iteration":932,"passed_time":21.51831214,"remaining_time":1.545259285},
{"learn":[0.2977610384],"iteration":933,"passed_time":21.53219052,"remaining_time":1.521546653},
{"learn":[0.2977254846],"iteration":934,"passed_time":21.54453011,"remaining_time":1.497748082},
{"learn":[0.2976894593],"iteration":935,"passed_time":21.56229238,"remaining_time":1.474344778},
{"learn":[0.2976551485],"iteration":936,"passed_time":21.57527491,"remaining_time":1.450632144},
{"learn":[0.2976254452],"iteration":937,"passed_time":21.59105241,"remaining_time":1.427127132},
{"learn":[0.2975862482],"iteration":938,"passed_time":21.61838974,"remaining_time":1.404389536},
{"learn":[0.297547394],"iteration":939,"passed_time":21.65738562,"remaining_time":1.382386316},
{"learn":[0.297515912],"iteration":940,"passed_time":21.67553219,"remaining_time":1.359039744},
{"learn":[0.2973114185],"iteration":941,"passed_time":21.68574755,"remaining_time":1.335215879},
{"learn":[0.2972610774],"iteration":942,"passed_time":21.70258886,"remaining_time":1.311821384},
{"learn":[0.297224302],"iteration":943,"passed_time":21.72182926,"remaining_time":1.288583091},
{"learn":[0.297190334],"iteration":944,"passed_time":21.73677565,"remaining_time":1.265103345},
{"learn":[0.2971543301],"iteration":945,"passed_time":21.74459481,"remaining_time":1.241234799},
{"learn":[0.2971163117],"iteration":946,"passed_time":21.75585732,"remaining_time":1.217592859},
{"learn":[0.2970835654],"iteration":947,"passed_time":21.79951606,"remaining_time":1.195754046},
{"learn":[0.2970504761],"iteration":948,"passed_time":21.84202647,"remaining_time":1.173807534},
{"learn":[0.2970072286],"iteration":949,"passed_time":21.925778,"remaining_time":1.153988316},
{"learn":[0.2969751465],"iteration":950,"passed_time":21.94875797,"remaining_time":1.130903407},
{"learn":[0.296937021],"iteration":951,"passed_time":21.96195716,"remaining_time":1.107325571},
{"learn":[0.2968993026],"iteration":952,"passed_time":21.98413553,"remaining_time":1.08421235},
{"learn":[0.2968703709],"iteration":953,"passed_time":21.99628243,"remaining_time":1.060617392},
{"learn":[0.296841525],"iteration":954,"passed_time":22.02982454,"remaining_time":1.038054559},
{"learn":[0.2968029279],"iteration":955,"passed_time":22.06153174,"remaining_time":1.015384306},
{"learn":[0.2967599162],"iteration":956,"passed_time":22.07862877,"remaining_time":0.9920387012},
{"learn":[0.2967275984],"iteration":957,"passed_time":22.08928888,"remaining_time":0.9684239384},
{"learn":[0.296687094],"iteration":958,"passed_time":22.10029796,"remaining_time":0.9448511119},
{"learn":[0.2966508544],"iteration":959,"passed_time":22.11275737,"remaining_time":0.9213648903},
{"learn":[0.2966136718],"iteration":960,"passed_time":22.14984208,"remaining_time":0.8989009794},
{"learn":[0.2965804754],"iteration":961,"passed_time":22.18852169,"remaining_time":0.8764696718},
{"learn":[0.2965451787],"iteration":962,"passed_time":22.19664534,"remaining_time":0.8528306102},
{"learn":[0.296518733],"iteration":963,"passed_time":22.21369334,"remaining_time":0.8295570126},
{"learn":[0.2964869939],"iteration":964,"passed_time":22.22039357,"remaining_time":0.8059210104},
{"learn":[0.2964527902],"iteration":965,"passed_time":22.22938521,"remaining_time":0.7824007216},
{"learn":[0.2964196152],"iteration":966,"passed_time":22.24299225,"remaining_time":0.7590679879},
{"learn":[0.296387276],"iteration":967,"passed_time":22.25595154,"remaining_time":0.7357339352},
{"learn":[0.296347886],"iteration":968,"passed_time":22.27450716,"remaining_time":0.7126003324},
{"learn":[0.2963136394],"iteration":969,"passed_time":22.28643545,"remaining_time":0.6892711994},
{"learn":[0.2962815788],"iteration":970,"passed_time":22.30082356,"remaining_time":0.6660390148},
{"learn":[0.296222151],"iteration":971,"passed_time":22.31547023,"remaining_time":0.6428324758},
{"learn":[0.2961882259],"iteration":972,"passed_time":22.32811784,"remaining_time":0.6195880593},
{"learn":[0.2961634947],"iteration":973,"passed_time":22.33736215,"remaining_time":0.5962745544},
{"learn":[0.2961286695],"iteration":974,"passed_time":22.3439031,"remaining_time":0.5729205923},
{"learn":[0.296097659],"iteration":975,"passed_time":22.35473493,"remaining_time":0.5497065965},
{"learn":[0.296065577],"iteration":976,"passed_time":22.37441002,"remaining_time":0.5267261316},
{"learn":[0.2960343522],"iteration":977,"passed_time":22.42326376,"remaining_time":0.5044087962},
{"learn":[0.2959914904],"iteration":978,"passed_time":22.46728023,"remaining_time":0.4819334881},
{"learn":[0.2958183289],"iteration":979,"passed_time":22.48548814,"remaining_time":0.4588875131},
{"learn":[0.2957857539],"iteration":980,"passed_time":22.50832193,"remaining_time":0.4359409957},
{"learn":[0.2957487642],"iteration":981,"passed_time":22.53816229,"remaining_time":0.4131231377},
{"learn":[0.2957210326],"iteration":982,"passed_time":22.65194212,"remaining_time":0.3917426409},
{"learn":[0.295685736],"iteration":983,"passed_time":22.70713228,"remaining_time":0.369221663},
{"learn":[0.2956505679],"iteration":984,"passed_time":22.74028893,"remaining_time":0.3462988161},
{"learn":[0.2956182073],"iteration":985,"passed_time":22.74968792,"remaining_time":0.3230178813},
{"learn":[0.2955863824],"iteration":986,"passed_time":22.77098853,"remaining_time":0.2999218347},
{"learn":[0.2955481283],"iteration":987,"passed_time":22.81445083,"remaining_time":0.2770985931},
{"learn":[0.2955155962],"iteration":988,"passed_time":22.86397417,"remaining_time":0.2543010271},
{"learn":[0.295481564],"iteration":989,"passed_time":22.88372896,"remaining_time":0.2311487774},
{"learn":[0.2954486461],"iteration":990,"passed_time":22.89383898,"remaining_time":0.207915793},
{"learn":[0.2954170999],"iteration":991,"passed_time":22.91040801,"remaining_time":0.1847613549},
{"learn":[0.2953823818],"iteration":992,"passed_time":22.9349988,"remaining_time":0.1616767287},
{"learn":[0.2952114277],"iteration":993,"passed_time":22.97006122,"remaining_time":0.138652281},
{"learn":[0.2951813601],"iteration":994,"passed_time":22.98589654,"remaining_time":0.1155070178},
{"learn":[0.2951485709],"iteration":995,"passed_time":23.00785646,"remaining_time":0.09240102996},
{"learn":[0.2951179462],"iteration":996,"passed_time":23.04309788,"remaining_time":0.06933730557},
{"learn":[0.295086207],"iteration":997,"passed_time":23.06422215,"remaining_time":0.04622088608},
{"learn":[0.2950538892],"iteration":998,"passed_time":23.07943657,"remaining_time":0.02310253911},
{"learn":[0.2950227716],"iteration":999,"passed_time":23.09053102,"remaining_time":0}
]}